Workbook
Name Annual_Depreciation_Tanker: 'Tanker Schedule'!$B$9
Name Base_NG_Demand: Inputs!$F$42:$F$42
Name Building_Cost_Pipeline: Inputs!$B$42
Name Building_Cost_Tanker: Inputs!$B$58
Name Carbon_Offset_Tanker: Inputs!$B$69
Name Contract_Mgmt_Fees: Inputs!$B$43
Name Conv_Factor: Inputs!$F$58:$F$58
Name D_i_Y: Inputs!$B$16
Name Days_Apr: Inputs!$B$28:$B$28
Name Days_Aug: Inputs!$B$32:$B$32
Name Days_Dec: Inputs!$B$36:$B$36
Name Days_Feb: Inputs!$B$26:$B$26
Name Days_Jan: Inputs!$B$25:$B$25
Name Days_Jul: Inputs!$B$31:$B$31
Name Days_Jun: Inputs!$B$30:$B$30
Name Days_Mar: Inputs!$B$27:$B$27
Name Days_May: Inputs!$B$29:$B$29
Name Days_Nov: Inputs!$B$35:$B$35
Name Days_Oct: Inputs!$B$34:$B$34
Name Days_Sept: Inputs!$B$33:$B$33
Name Demand_Increase: Inputs!$F$18
Name Discount_Rate: Inputs!$F$23
Name Employee_Deduction_Rate: Inputs!$B$75:$B$75
Name Employer_Social_Insurance_Rate: Inputs!$B$74:$B$74
Name First_Yr: Inputs!$B$19:$B$19
Name Fuel_Pipeline: Inputs!$B$51
Name General_Main_Eng: Inputs!$B$50:$B$50
Name General_Pipeline: Inputs!$B$52
Name General_Tanker: Inputs!$B$63
Name Heavy_Fuel_Oil: Inputs!$B$66
Name Increment: Inputs!$B$14
Name Inflation_Annual: Inputs!$F$15
Name Inflation_Carbon_Offset: Inputs!$F$16
Name Insurance_Cov: Inputs!$F$65:$F$65
Name Insurance_Pipeline: Inputs!$B$48
Name Insurance_Tanker: Inputs!$B$62
Name LNG_Tanker_Cap: Inputs!$F$62:$F$62
Name Loan_Payment_Term: Inputs!$F$22
Name M_i_Y: Inputs!$B$15
Name Min_Cash_Balance: Inputs!$F$24
Name Nil: Inputs!$F$19:$F$19
Name Operating_Exp: Inputs!$B$68
Name Operations_Mgmt: Inputs!$B$49
Name Pipeline_TotalCost: Inputs!$B$44:$B$44
Name Port_Fees: Inputs!$B$65
Name Purch_price_LNG: Inputs!$F$60:$F$60
Name Purch_price_NG: Inputs!$F$43:$F$43
Name Salvage_Val_Pipeline: Inputs!$B$45
Name Salvage_Val_Tanker: Inputs!$B$59
Name SBU_Insurance: Inputs!$F$66:$F$66
Name Sell_price_LNG: Inputs!$F$61:$F$61
Name Sell_price_NG: Inputs!$F$44:$F$44
Name Set_Up_Year: Inputs!$B$17
Name Stores_Spares_Lube: Inputs!$B$64
Name Tons_Req_a_Trip: Inputs!$B$67
Name Total_Crew_Costs: Inputs!$B$72
Name Total_Years: Inputs!$B$20:$B$20
Name Useful_Life: Inputs!$F$27
Name Y3_Port_Repair: Inputs!$F$64:$F$64
Name Y5_Carbon_Increase: Inputs!$F$17:$F$17

Sheet Cover Page
D1: DATA MODEL: QATAR ENERGY CASE
A3: Business Proposition:
A4: Qatar Energy aims to deliver a cost-effective, financially advantageous method for supplying natural gas to Bahrain over a 30-year period. Using our financial model, we can compare the trade-off between the high up-front capital cost of the pipeline ($520 million) and the operational flexibility of the Q-Max LNG Tanker ($250 million). The goal is to maximize shareholder wealth by selecting the delivery method (i.e., Pipeline or Tanker) that offers the highest capital efficiency and other return metrics, ensuring that these returns exceed the 4% cost of capital provided by the National Bank of Qatar.
A10: Executive Summary:
A11: Based on our 30-year competitive financial analysis, the Q-Max Tanker (LNG) is the recommended delivery method. When comparing the 30-year NPV, it outperforms the pipeline across our primary financial metrics, offering higher wealth and faster capital recovery for investors.
A15: Strategeic Financial Findings (Pipeline vs. Tanker)
D16: Pipeline (NG) | F16: Tanker (LNG)
A17: NPV | D17: ='NPV (Y2-Y31)'!D78 -> 1.6938693e+09 | F17: ='NPV (Y2-Y31)'!F78 -> 1.980071e+09
A18: IRR | D18: =IRR('NPV (Y2-Y31)'!C47:C77) -> 0.1852723 | F18: =IRR('NPV (Y2-Y31)'!E47:E77) -> 0.40670795
A19: Payback Period | D19: {=(Set_Up_Year+Increment+Increment+Increment+Increment)+(Pipeline_TotalCost-SUM('NPV (Y2-Y31)'!C48:C52))/'NPV (Y2-Y31)'!C53} -> 5.7243897 | F19: =(Set_Up_Year+Increment)+(Building_Cost_Tanker-'NPV (Y2-Y31)'!E48-'NPV (Y2-Y31)'!E49)/'NPV (Y2-Y31)'!E50 -> 2.5157507
A20: Profitability Index (PI) | D20: {='NPV (Y2-Y31)'!D78/Pipeline_TotalCost} -> 3.257441 | F20: ='NPV (Y2-Y31)'!F78/Building_Cost_Tanker -> 7.9202841
A22: Key Insights & Risks
A23: Operational Resilience: In Year 3, the port damage was 90% covered by insurance, therefore, an additional $500,000 to repair the port had to be paid by Qatar Energy. Despite the port damage, net income increased from Year 2 of ~80 million to Year 3 of ~81 million. Additionally, with carbon costs doubling in Year 5 to over $74 million, the Tanker remains highly profitable, with Net Income in Year 5 of ~47 million. Confirming these situations indicates our model can withstand economic shifts without threatening the project's success.
A27: Cash Position: By the end of Year 5, the Tanker generates an ending cash balance of $368,806,012, which exceeds the required $10 million minimum reserve.
A29: Capital Efficiency (PI & IRR): The tanker requires an initial capital of 250 million, which is 52% less than the Pipeline's initial investment of $520 millipn. The tanker method provides a PI of 7.92 (compared to the pipeline PI of 3.26), indicating it is twice as efficient an investment and would provide a 7.92x return per dollar.
A32: Wealth (NPV): The tanker (NPV of 1,980,071,025) creates $286,201,680 more in total NPV (of 1,693,869,345) than the pipeline, due to its lower initial investment and the favourable price-to-volume ratio of LNG.
A34: Cash Recovery (Payback): The tanker reaches a break-even point in 2.52 years of operations, whereas the pipeline takes 5.72 years, representing significantly lower/higher capital-lockup risk.
A36: Recomendation:
A37: It is recommended that Qatar Energy proceed with the Q-Max Tanker delivery method. It offers higher NPV and PI, indicating that Qatar Energy maximizes the value of its sovereign natural gas assets while maintaining superior liquidity and capital flexibility.

Sheet Inputs
A1: QATAR ENERGY
A2: INPUTS - PIPELINE & TANKER
A4: Color Key
A5: Black = Scaffolding, calculated values (do not overwrite)
A6: Red = Editable data
A7: Black on blue = Owner's decision
B8: Grey shade - no input
A9: Green = Calculated value, do not overwrite
A11: GENERAL AND SHARED INPUTS
A13: TIME AND DATE | E13: ECONOMICS
A14: Increment | B14: 1 | E14: Inflations (compounded):
A15: Months in Year | B15: 12 | E15: Annual Inflation | F15: 0.015
A16: Days in Year | B16: 365.25 | E16: Carbon Offset Inflation | F16: 0.039
A17: Set Up Year | B17: 1 | E17: Carbon Offset Inflation (Special - Year 5) | F17: 2
E18: Demand Increase Rate | F18: 0.005
A19: First Year of Ops | B19: 2 | E19: Nil | F19: 0
A20: Total Years of Ops | B20: 30
A21: Billing Day | B21: 21 | E21: FINANCE
A22: Dormant Months Y1 | B22: 1 | E22: Loan Payment Term (year) | F22: 30
E23: Discount Rate (compounded annually) | F23: 0.04
A24: Days in Month | E24: Minimum Cash Balance | F24: 10000000
A25: January | B25: 31
A26: February | B26: 28.25 | E26: CAPITAL ASSETS
A27: March | B27: 31 | E27: Useful Life (years) | F27: 30
A28: April | B28: 30
A29: May | B29: 31
A30: June | B30: 30
A31: July | B31: 31
A32: August | B32: 31
A33: September | B33: 30
A34: October | B34: 31
A35: November | B35: 30
A36: December | B36: 31
A39: PIPELINE INPUTS
A41: CAPITAL ASSETS | E41: PRICING, DEMAND AND SUPPLIES
A42: Pipeline Building Cost | B42: 400000000 | E42: Base NG Demand (annual, starting Y2) | F42: 17000000000
A43: Contract Management Fees | B43: 120000000 | E43: NG Purchase price, per cubic meter | F43: 0.046
A44: Total Pipeline Cost | B44: =Contract_Mgmt_Fees+Building_Cost_Pipeline -> 520000000 | E44: NG Selling price, per cubic meter | F44: 0.052
A45: Pipeline Salvage Value (net of decommissioning costs, Y31) | B45: 15000000
A47: INFLATABLE COSTS
A48: Pipeline Insurance (annual, paid advance Jan 1 yearly) | B48: 2200000
A49: Operations Management (annual) | B49: 1000000
A50: General Maintenance and Engineering (annual) | B50: 12000000
A51: Fuel for Compression and Pumping (annual, paid monthly) | B51: 4700000
A52: Carbon Offset (per pipeline, annual, paid monthly) | B52: 800000
A55: TANKER INPUTS
A57: CAPITAL ASSETS | E57: PRICING, DEMAND AND SUPPLIES
A58: Tanker Building Cost | B58: 250000000 | E58: NG-to-LNG Conversion Factor | F58: 600
A59: Tanker Salvage Value | B59: 20000000 | E59: Base LNG Demand (annual, starting Y2) | F59: 28330000
E60: LNG Purchase price, per cubic meter | F60: 22
A61: INFLATABLE COSTS | E61: LNG Selling price, per cubic meter | F61: 28
A62: Tanker Insurance | B62: 1800000 | E62: LNG Tanker Capacity per Trip | F62: 260000
A63: General Maintenance and Engineering (annual) | B63: 2000000 | E63: Special Events:
A64: Stores, spares, and lubricants (annual) | B64: 2000000 | E64: Year 3 Port Repair | F64: 5000000
A65: Port Fees (per round trip) | B65: 220000 | E65: Insurance Coverage % | F65: 0.9
A66: Heavy Fuel Oil (per ton) | B66: 380
A67: Tons Required per Round Trip | B67: 24
A68: Operating Expenses (per round trip) | B68: 40000
A69: Carbon Offset (per year, per ship) | B69: 33000000
A71: EMPLOYMENT COSTS
A72: Total Crew Costs (annual) | B72: 3500000
A73: Social Insurance Costs (remitted in the following month):
A74: Employer Social Insurance | B74: 0.14
A75: Employee Deduction | B75: 0.07

Sheet Pipeline Schedule
A1: QATAR ENERGY
A2: PIPELINE SCHEDULE
A4: CAPITAL ASSETS
B5: Pipeline
A6: Capital Assets | B6: {=Pipeline_TotalCost} -> 520000000
A7: Useful Life | B7: =Useful_Life -> 30
A8: Salvage value | B8: =Salvage_Val_Pipeline -> 15000000
A9: Annual Depreciation | B9: {=(Pipeline_TotalCost-Salvage_Val_Pipeline)/Useful_Life} -> 16833333
A11: DEPRECIATION
A12: Year | B12: Begininng Value ($) | C12: Depreciation Amount ($) | D12: Remaining Amount ($)
A13: =Increment -> 1
A14: =A13+Increment -> 2 | B14: {=Pipeline_TotalCost} -> 520000000 | C14: =$B$9 -> 16833333 | D14: =B14-C14 -> 5.0316667e+08
A15: =A14+Increment -> 3 | B15: =D14 -> 5.0316667e+08 | C15: =$B$9 -> 16833333 | D15: =B15-C15 -> 4.8633333e+08
A16: =A15+Increment -> 4 | B16: =D15 -> 4.8633333e+08 | C16: =$B$9 -> 16833333 | D16: =B16-C16 -> 4.695e+08
A17: =A16+Increment -> 5 | B17: =D16 -> 4.695e+08 | C17: =$B$9 -> 16833333 | D17: =B17-C17 -> 4.5266667e+08
A18: =A17+Increment -> 6 | B18: =D17 -> 4.5266667e+08 | C18: =$B$9 -> 16833333 | D18: =B18-C18 -> 4.3583333e+08
A19: =A18+Increment -> 7 | B19: =D18 -> 4.3583333e+08 | C19: =$B$9 -> 16833333 | D19: =B19-C19 -> 4.19e+08
A20: =A19+Increment -> 8 | B20: =D19 -> 4.19e+08 | C20: =$B$9 -> 16833333 | D20: =B20-C20 -> 4.0216667e+08
A21: =A20+Increment -> 9 | B21: =D20 -> 4.0216667e+08 | C21: =$B$9 -> 16833333 | D21: =B21-C21 -> 3.8533333e+08
A22: =A21+Increment -> 10 | B22: =D21 -> 3.8533333e+08 | C22: =$B$9 -> 16833333 | D22: =B22-C22 -> 3.685e+08
A23: =A22+Increment -> 11 | B23: =D22 -> 3.685e+08 | C23: =$B$9 -> 16833333 | D23: =B23-C23 -> 3.5166667e+08
A24: =A23+Increment -> 12 | B24: =D23 -> 3.5166667e+08 | C24: =$B$9 -> 16833333 | D24: =B24-C24 -> 3.3483333e+08
A25: =A24+Increment -> 13 | B25: =D24 -> 3.3483333e+08 | C25: =$B$9 -> 16833333 | D25: =B25-C25 -> 3.18e+08
A26: =A25+Increment -> 14 | B26: =D25 -> 3.18e+08 | C26: =$B$9 -> 16833333 | D26: =B26-C26 -> 3.0116667e+08
... A43: =A42+Increment -> 31 | B43: =D42 -> 31833333 | C43: =$B$9 -> 16833333 | D43: =B43-C43 -> 15000000
A46: NATURAL GAS (NG) REVENUE | F46: NATURAL GAS (NG) PURCHASE
A47: Year | B47: NG Sales Voulme ($) | C47: NG Selling Price ($/M3) | D47: NG Total Revenue ($) | F47: Year | G47: NG Purchase Voulme ($) | H47: NG Cost Price ($/M3) | I47: NG Total Cost ($)
A48: =Increment -> 1 | F48: =Increment -> 1
A49: =A48+Increment -> 2 | B49: {=Base_NG_Demand*(Increment+Demand_Increase)^(A49-First_Yr)} -> 17000000000 | C49: {=Sell_price_NG*(Inflation_Annual+Increment)^(A49-First_Yr)} -> 0.052 | D49: =B49*C49 -> 884000000 | F49: =F48+Increment -> 2 | G49: {=Base_NG_Demand*(Increment+Demand_Increase)^(A49-First_Yr)} -> 17000000000 | H49: {=Purch_price_NG*(Inflation_Annual+Increment)^(F49-First_Yr)} -> 0.046 | I49: =G49*H49 -> 782000000
A50: =A49+Increment -> 3 | B50: {=Base_NG_Demand*(Increment+Demand_Increase)^(A50-First_Yr)} -> 1.7085e+10 | C50: {=Sell_price_NG*(Inflation_Annual+Increment)^(A50-First_Yr)} -> 0.05278 | D50: =B50*C50 -> 9.017463e+08 | F50: =F49+Increment -> 3 | G50: {=Base_NG_Demand*(Increment+Demand_Increase)^(A50-First_Yr)} -> 1.7085e+10 | H50: {=Purch_price_NG*(Inflation_Annual+Increment)^(F50-First_Yr)} -> 0.04669 | I50: =G50*H50 -> 7.9769865e+08
A51: =A50+Increment -> 4 | B51: {=Base_NG_Demand*(Increment+Demand_Increase)^(A51-First_Yr)} -> 1.7170425e+10 | C51: {=Sell_price_NG*(Inflation_Annual+Increment)^(A51-First_Yr)} -> 0.0535717 | D51: =B51*C51 -> 9.1984886e+08 | F51: =F50+Increment -> 4 | G51: {=Base_NG_Demand*(Increment+Demand_Increase)^(A51-First_Yr)} -> 1.7170425e+10 | H51: {=Purch_price_NG*(Inflation_Annual+Increment)^(F51-First_Yr)} -> 0.04739035 | I51: =G51*H51 -> 8.1371245e+08
A52: =A51+Increment -> 5 | B52: {=Base_NG_Demand*(Increment+Demand_Increase)^(A52-First_Yr)} -> 1.7256277e+10 | C52: {=Sell_price_NG*(Inflation_Annual+Increment)^(A52-First_Yr)} -> 0.054375275 | D52: =B52*C52 -> 9.3831482e+08 | F52: =F51+Increment -> 5 | G52: {=Base_NG_Demand*(Increment+Demand_Increase)^(A52-First_Yr)} -> 1.7256277e+10 | H52: {=Purch_price_NG*(Inflation_Annual+Increment)^(F52-First_Yr)} -> 0.048101205 | I52: =G52*H52 -> 8.3004773e+08
A53: =A52+Increment -> 6 | B53: {=Base_NG_Demand*(Increment+Demand_Increase)^(A53-First_Yr)} -> 1.7342559e+10 | C53: {=Sell_price_NG*(Inflation_Annual+Increment)^(A53-First_Yr)} -> 0.055190905 | D53: =B53*C53 -> 9.5715149e+08 | F53: =F52+Increment -> 6 | G53: {=Base_NG_Demand*(Increment+Demand_Increase)^(A53-First_Yr)} -> 1.7342559e+10 | H53: {=Purch_price_NG*(Inflation_Annual+Increment)^(F53-First_Yr)} -> 0.048822723 | I53: =G53*H53 -> 8.4671094e+08
A54: =A53+Increment -> 7 | B54: {=Base_NG_Demand*(Increment+Demand_Increase)^(A54-First_Yr)} -> 1.7429271e+10 | C54: {=Sell_price_NG*(Inflation_Annual+Increment)^(A54-First_Yr)} -> 0.056018768 | D54: =B54*C54 -> 9.7636631e+08 | F54: =F53+Increment -> 7 | G54: {=Base_NG_Demand*(Increment+Demand_Increase)^(A54-First_Yr)} -> 1.7429271e+10 | H54: {=Purch_price_NG*(Inflation_Annual+Increment)^(F54-First_Yr)} -> 0.049555064 | I54: =G54*H54 -> 8.6370866e+08
A55: =A54+Increment -> 8 | B55: {=Base_NG_Demand*(Increment+Demand_Increase)^(A55-First_Yr)} -> 1.7516418e+10 | C55: {=Sell_price_NG*(Inflation_Annual+Increment)^(A55-First_Yr)} -> 0.05685905 | D55: =B55*C55 -> 9.9596686e+08 | F55: =F54+Increment -> 8 | G55: {=Base_NG_Demand*(Increment+Demand_Increase)^(A55-First_Yr)} -> 1.7516418e+10 | H55: {=Purch_price_NG*(Inflation_Annual+Increment)^(F55-First_Yr)} -> 0.05029839 | I55: =G55*H55 -> 8.8104761e+08
A56: =A55+Increment -> 9 | B56: {=Base_NG_Demand*(Increment+Demand_Increase)^(A56-First_Yr)} -> 1.7604e+10 | C56: {=Sell_price_NG*(Inflation_Annual+Increment)^(A56-First_Yr)} -> 0.057711935 | D56: =B56*C56 -> 1.0159609e+09 | F56: =F55+Increment -> 9 | G56: {=Base_NG_Demand*(Increment+Demand_Increase)^(A56-First_Yr)} -> 1.7604e+10 | H56: {=Purch_price_NG*(Inflation_Annual+Increment)^(F56-First_Yr)} -> 0.051052866 | I56: =G56*H56 -> 8.9873464e+08
A57: =A56+Increment -> 10 | B57: {=Base_NG_Demand*(Increment+Demand_Increase)^(A57-First_Yr)} -> 1.769202e+10 | C57: {=Sell_price_NG*(Inflation_Annual+Increment)^(A57-First_Yr)} -> 0.058577615 | D57: =B57*C57 -> 1.0363563e+09 | F57: =F56+Increment -> 10 | G57: {=Base_NG_Demand*(Increment+Demand_Increase)^(A57-First_Yr)} -> 1.769202e+10 | H57: {=Purch_price_NG*(Inflation_Annual+Increment)^(F57-First_Yr)} -> 0.051818659 | I57: =G57*H57 -> 9.1677674e+08
A58: =A57+Increment -> 11 | B58: {=Base_NG_Demand*(Increment+Demand_Increase)^(A58-First_Yr)} -> 1.778048e+10 | C58: {=Sell_price_NG*(Inflation_Annual+Increment)^(A58-First_Yr)} -> 0.059456279 | D58: =B58*C58 -> 1.0571612e+09 | F58: =F57+Increment -> 11 | G58: {=Base_NG_Demand*(Increment+Demand_Increase)^(A58-First_Yr)} -> 1.778048e+10 | H58: {=Purch_price_NG*(Inflation_Annual+Increment)^(F58-First_Yr)} -> 0.052595939 | I58: =G58*H58 -> 9.3518103e+08
A59: =A58+Increment -> 12 | B59: {=Base_NG_Demand*(Increment+Demand_Increase)^(A59-First_Yr)} -> 1.7869382e+10 | C59: {=Sell_price_NG*(Inflation_Annual+Increment)^(A59-First_Yr)} -> 0.060348123 | D59: =B59*C59 -> 1.0783837e+09 | F59: =F58+Increment -> 12 | G59: {=Base_NG_Demand*(Increment+Demand_Increase)^(A59-First_Yr)} -> 1.7869382e+10 | H59: {=Purch_price_NG*(Inflation_Annual+Increment)^(F59-First_Yr)} -> 0.053384878 | I59: =G59*H59 -> 9.5395479e+08
A60: =A59+Increment -> 13 | B60: {=Base_NG_Demand*(Increment+Demand_Increase)^(A60-First_Yr)} -> 1.7958729e+10 | C60: {=Sell_price_NG*(Inflation_Annual+Increment)^(A60-First_Yr)} -> 0.061253345 | D60: =B60*C60 -> 1.1000322e+09 | F60: =F59+Increment -> 13 | G60: {=Base_NG_Demand*(Increment+Demand_Increase)^(A60-First_Yr)} -> 1.7958729e+10 | H60: {=Purch_price_NG*(Inflation_Annual+Increment)^(F60-First_Yr)} -> 0.054185651 | I60: =G60*H60 -> 9.7310543e+08
... A78: =A77+Increment -> 31 | B78: {=Base_NG_Demand*(Increment+Demand_Increase)^(A78-First_Yr)} -> 1.9645574e+10 | C78: {=Sell_price_NG*(Inflation_Annual+Increment)^(A78-First_Yr)} -> 0.080078987 | D78: =B78*C78 -> 1.5731976e+09 | F78: =F77+Increment -> 31 | G78: {=Base_NG_Demand*(Increment+Demand_Increase)^(A78-First_Yr)} -> 1.9645574e+10 | H78: {=Purch_price_NG*(Inflation_Annual+Increment)^(F78-First_Yr)} -> 0.070839104 | I78: =G78*H78 -> 1.3916748e+09
A81: FUEL COMPRESSION AND PUMPING EXPENSE
A82: Year | B82: Expense Per Year ($) | C82: Expense Per Month ($)
A83: =Increment -> 1
A84: =A83+Increment -> 2 | B84: =Fuel_Pipeline -> 4700000 | C84: =B84*(Increment/M_i_Y) -> 391666.67
A85: =A84+Increment -> 3 | B85: =B84*(Inflation_Annual+Increment) -> 4770500 | C85: =B85*(Increment/M_i_Y) -> 397541.67
A86: =A85+Increment -> 4 | B86: =B85*(Inflation_Annual+Increment) -> 4842057.5 | C86: =B86*(Increment/M_i_Y) -> 403504.79
A87: =A86+Increment -> 5 | B87: =B86*(Inflation_Annual+Increment) -> 4914688.4 | C87: =B87*(Increment/M_i_Y) -> 409557.36
A88: =A87+Increment -> 6 | B88: =B87*(Inflation_Annual+Increment) -> 4988408.7 | C88: =B88*(Increment/M_i_Y) -> 415700.72
A89: =A88+Increment -> 7 | B89: =B88*(Inflation_Annual+Increment) -> 5063234.8 | C89: =B89*(Increment/M_i_Y) -> 421936.23
A90: =A89+Increment -> 8 | B90: =B89*(Inflation_Annual+Increment) -> 5139183.3 | C90: =B90*(Increment/M_i_Y) -> 428265.28
A91: =A90+Increment -> 9 | B91: =B90*(Inflation_Annual+Increment) -> 5216271.1 | C91: =B91*(Increment/M_i_Y) -> 434689.26
A92: =A91+Increment -> 10 | B92: =B91*(Inflation_Annual+Increment) -> 5294515.2 | C92: =B92*(Increment/M_i_Y) -> 441209.6
A93: =A92+Increment -> 11 | B93: =B92*(Inflation_Annual+Increment) -> 5373932.9 | C93: =B93*(Increment/M_i_Y) -> 447827.74
A94: =A93+Increment -> 12 | B94: =B93*(Inflation_Annual+Increment) -> 5454541.9 | C94: =B94*(Increment/M_i_Y) -> 454545.16
A95: =A94+Increment -> 13 | B95: =B94*(Inflation_Annual+Increment) -> 5536360 | C95: =B95*(Increment/M_i_Y) -> 461363.33
A96: =A95+Increment -> 14 | B96: =B95*(Inflation_Annual+Increment) -> 5619405.4 | C96: =B96*(Increment/M_i_Y) -> 468283.78
... A113: =A112+Increment -> 31 | B113: =B112*(Inflation_Annual+Increment) -> 7237908.4 | C113: =B113*(Increment/M_i_Y) -> 603159.03
A116: BANK LOAN
A117: Annual Payment | C117: {=PMT(Discount_Rate,Total_Years,-B121,,0)} -> 31324637
H118: Monthly interest expense - Y1
A119: Year | B119: Principal | C119: Interest | D119: Payment | E119: Amortization | F119: Ending balance | H119: Month | I119: Outstanding balance | J119: Interest expense
A120: =Increment -> 1 | B120: {=Pipeline_TotalCost+Min_Cash_Balance} -> 530000000 | C120: =J132 -> 11666667 | F120: =B120+C120 -> 5.4166667e+08 | H120: January | I120: {=Pipeline_TotalCost/M_i_Y+Min_Cash_Balance} -> 53333333 | J120: =I120*Discount_Rate/M_i_Y -> 177777.78
A121: =A120+Increment -> 2 | B121: =F120 -> 5.4166667e+08 | C121: =B121*Discount_Rate -> 21666667 | D121: =$C$117 -> 31324637 | E121: =D121-C121 -> 9657970.4 | F121: =B121-E121 -> 5.320087e+08 | H121: February | I121: {=Pipeline_TotalCost/M_i_Y+I120} -> 96666667 | J121: =I121*Discount_Rate/M_i_Y -> 322222.22
A122: =A121+Increment -> 3 | B122: =F121 -> 5.320087e+08 | C122: =B122*Discount_Rate -> 21280348 | D122: =$C$117 -> 31324637 | E122: =D122-C122 -> 10044289 | F122: =B122-E122 -> 5.2196441e+08 | H122: March | I122: {=Pipeline_TotalCost/M_i_Y+I121} -> 140000000 | J122: =I122*Discount_Rate/M_i_Y -> 466666.67
A123: =A122+Increment -> 4 | B123: =F122 -> 5.2196441e+08 | C123: =B123*Discount_Rate -> 20878576 | D123: =$C$117 -> 31324637 | E123: =D123-C123 -> 10446061 | F123: =B123-E123 -> 5.1151835e+08 | H123: April | I123: {=Pipeline_TotalCost/M_i_Y+I122} -> 1.8333333e+08 | J123: =I123*Discount_Rate/M_i_Y -> 611111.11
A124: =A123+Increment -> 5 | B124: =F123 -> 5.1151835e+08 | C124: =B124*Discount_Rate -> 20460734 | D124: =$C$117 -> 31324637 | E124: =D124-C124 -> 10863903 | F124: =B124-E124 -> 5.0065444e+08 | H124: May | I124: {=Pipeline_TotalCost/M_i_Y+I123} -> 2.2666667e+08 | J124: =I124*Discount_Rate/M_i_Y -> 755555.56
A125: =A124+Increment -> 6 | B125: =F124 -> 5.0065444e+08 | C125: =B125*Discount_Rate -> 20026178 | D125: =$C$117 -> 31324637 | E125: =D125-C125 -> 11298459 | F125: =B125-E125 -> 4.8935598e+08 | H125: June | I125: {=Pipeline_TotalCost/M_i_Y+I124} -> 270000000 | J125: =I125*Discount_Rate/M_i_Y -> 900000
A126: =A125+Increment -> 7 | B126: =F125 -> 4.8935598e+08 | C126: =B126*Discount_Rate -> 19574239 | D126: =$C$117 -> 31324637 | E126: =D126-C126 -> 11750398 | F126: =B126-E126 -> 4.7760559e+08 | H126: July | I126: {=Pipeline_TotalCost/M_i_Y+I125} -> 3.1333333e+08 | J126: =I126*Discount_Rate/M_i_Y -> 1044444.4
A127: =A126+Increment -> 8 | B127: =F126 -> 4.7760559e+08 | C127: =B127*Discount_Rate -> 19104223 | D127: =$C$117 -> 31324637 | E127: =D127-C127 -> 12220414 | F127: =B127-E127 -> 4.6538517e+08 | H127: August | I127: {=Pipeline_TotalCost/M_i_Y+I126} -> 3.5666667e+08 | J127: =I127*Discount_Rate/M_i_Y -> 1188888.9
A128: =A127+Increment -> 9 | B128: =F127 -> 4.6538517e+08 | C128: =B128*Discount_Rate -> 18615407 | D128: =$C$117 -> 31324637 | E128: =D128-C128 -> 12709230 | F128: =B128-E128 -> 4.5267594e+08 | H128: September | I128: {=Pipeline_TotalCost/M_i_Y+I127} -> 4e+08 | J128: =I128*Discount_Rate/M_i_Y -> 1333333.3
A129: =A128+Increment -> 10 | B129: =F128 -> 4.5267594e+08 | C129: =B129*Discount_Rate -> 18107038 | D129: =$C$117 -> 31324637 | E129: =D129-C129 -> 13217599 | F129: =B129-E129 -> 4.3945834e+08 | H129: October | I129: {=Pipeline_TotalCost/M_i_Y+I128} -> 4.4333333e+08 | J129: =I129*Discount_Rate/M_i_Y -> 1477777.8
A130: =A129+Increment -> 11 | B130: =F129 -> 4.3945834e+08 | C130: =B130*Discount_Rate -> 17578334 | D130: =$C$117 -> 31324637 | E130: =D130-C130 -> 13746303 | F130: =B130-E130 -> 4.2571204e+08 | H130: November | I130: {=Pipeline_TotalCost/M_i_Y+I129} -> 4.8666667e+08 | J130: =I130*Discount_Rate/M_i_Y -> 1622222.2
A131: =A130+Increment -> 12 | B131: =F130 -> 4.2571204e+08 | C131: =B131*Discount_Rate -> 17028482 | D131: =$C$117 -> 31324637 | E131: =D131-C131 -> 14296155 | F131: =B131-E131 -> 4.1141588e+08 | H131: December | I131: {=Pipeline_TotalCost/M_i_Y+I130} -> 5.3e+08 | J131: =I131*Discount_Rate/M_i_Y -> 1766666.7
A132: =A131+Increment -> 13 | B132: =F131 -> 4.1141588e+08 | C132: =B132*Discount_Rate -> 16456635 | D132: =$C$117 -> 31324637 | E132: =D132-C132 -> 14868002 | F132: =B132-E132 -> 3.9654788e+08 | H132: Total | J132: =SUM(J120:J131) -> 11666667
A133: =A132+Increment -> 14 | B133: =F132 -> 3.9654788e+08 | C133: =B133*Discount_Rate -> 15861915 | D133: =$C$117 -> 31324637 | E133: =D133-C133 -> 15462722 | F133: =B133-E133 -> 3.8108516e+08
A134: =A133+Increment -> 15 | B134: =F133 -> 3.8108516e+08 | C134: =B134*Discount_Rate -> 15243406 | D134: =$C$117 -> 31324637 | E134: =D134-C134 -> 16081231 | F134: =B134-E134 -> 3.6500393e+08
A135: =A134+Increment -> 16 | B135: =F134 -> 3.6500393e+08 | C135: =B135*Discount_Rate -> 14600157 | D135: =$C$117 -> 31324637 | E135: =D135-C135 -> 16724480 | F135: =B135-E135 -> 3.4827945e+08
A136: =A135+Increment -> 17 | B136: =F135 -> 3.4827945e+08 | C136: =B136*Discount_Rate -> 13931178 | D136: =$C$117 -> 31324637 | E136: =D136-C136 -> 17393459 | F136: =B136-E136 -> 3.3088599e+08
A137: =A136+Increment -> 18 | B137: =F136 -> 3.3088599e+08 | C137: =B137*Discount_Rate -> 13235440 | D137: =$C$117 -> 31324637 | E137: =D137-C137 -> 18089197 | F137: =B137-E137 -> 3.1279679e+08
A138: =A137+Increment -> 19 | B138: =F137 -> 3.1279679e+08 | C138: =B138*Discount_Rate -> 12511872 | D138: =$C$117 -> 31324637 | E138: =D138-C138 -> 18812765 | F138: =B138-E138 -> 2.9398403e+08
A139: =A138+Increment -> 20 | B139: =F138 -> 2.9398403e+08 | C139: =B139*Discount_Rate -> 11759361 | D139: =$C$117 -> 31324637 | E139: =D139-C139 -> 19565276 | F139: =B139-E139 -> 2.7441875e+08
A140: =A139+Increment -> 21 | B140: =F139 -> 2.7441875e+08 | C140: =B140*Discount_Rate -> 10976750 | D140: =$C$117 -> 31324637 | E140: =D140-C140 -> 20347887 | F140: =B140-E140 -> 2.5407087e+08
A141: =A140+Increment -> 22 | B141: =F140 -> 2.5407087e+08 | C141: =B141*Discount_Rate -> 10162835 | D141: =$C$117 -> 31324637 | E141: =D141-C141 -> 21161802 | F141: =B141-E141 -> 2.3290906e+08
A142: =A141+Increment -> 23 | B142: =F141 -> 2.3290906e+08 | C142: =B142*Discount_Rate -> 9316362.6 | D142: =$C$117 -> 31324637 | E142: =D142-C142 -> 22008274 | F142: =B142-E142 -> 2.1090079e+08
A143: =A142+Increment -> 24 | B143: =F142 -> 2.1090079e+08 | C143: =B143*Discount_Rate -> 8436031.6 | D143: =$C$117 -> 31324637 | E143: =D143-C143 -> 22888605 | F143: =B143-E143 -> 1.8801218e+08
A144: =A143+Increment -> 25 | B144: =F143 -> 1.8801218e+08 | C144: =B144*Discount_Rate -> 7520487.4 | D144: =$C$117 -> 31324637 | E144: =D144-C144 -> 23804150 | F144: =B144-E144 -> 1.6420803e+08
... A150: =A149+Increment -> 31 | B150: =F149 -> 30119843 | C150: =B150*Discount_Rate -> 1204793.7 | D150: =$C$117 -> 31324637 | E150: =D150-C150 -> 30119843 | F150: =B150-E150 -> -2.9429793e-07

Sheet Tanker Schedule
A1: QATAR ENERGY
A2: TANKER SCHEDULE
A4: CAPITAL ASSETS
B5: Tanker
A6: Capital Assets | B6: =Building_Cost_Tanker -> 250000000
A7: Useful Life | B7: =Useful_Life -> 30
A8: Salvage value | B8: =Salvage_Val_Tanker -> 20000000
A9: Annual Depreciation | B9: =(Building_Cost_Tanker-Salvage_Val_Tanker)/Useful_Life -> 7666666.7
A11: DEPRECIATION SCHEDULE
A12: Year | B12: Begininng Value | C12: Depreciation Amount | D12: Remaining Amount
A13: =Increment -> 1
A14: =A13+Increment -> 2 | B14: =B6 -> 250000000 | C14: =$B$9 -> 7666666.7 | D14: =B14-C14 -> 2.4233333e+08
A15: =A14+Increment -> 3 | B15: =D14 -> 2.4233333e+08 | C15: =$B$9 -> 7666666.7 | D15: =B15-C15 -> 2.3466667e+08
A16: =A15+Increment -> 4 | B16: =D15 -> 2.3466667e+08 | C16: =$B$9 -> 7666666.7 | D16: =B16-C16 -> 2.27e+08
A17: =A16+Increment -> 5 | B17: =D16 -> 2.27e+08 | C17: =$B$9 -> 7666666.7 | D17: =B17-C17 -> 2.1933333e+08
A18: =A17+Increment -> 6 | B18: =D17 -> 2.1933333e+08 | C18: =$B$9 -> 7666666.7 | D18: =B18-C18 -> 2.1166667e+08
A19: =A18+Increment -> 7 | B19: =D18 -> 2.1166667e+08 | C19: =$B$9 -> 7666666.7 | D19: =B19-C19 -> 2.04e+08
A20: =A19+Increment -> 8 | B20: =D19 -> 2.04e+08 | C20: =$B$9 -> 7666666.7 | D20: =B20-C20 -> 1.9633333e+08
A21: =A20+Increment -> 9 | B21: =D20 -> 1.9633333e+08 | C21: =$B$9 -> 7666666.7 | D21: =B21-C21 -> 1.8866667e+08
A22: =A21+Increment -> 10 | B22: =D21 -> 1.8866667e+08 | C22: =$B$9 -> 7666666.7 | D22: =B22-C22 -> 1.81e+08
A23: =A22+Increment -> 11 | B23: =D22 -> 1.81e+08 | C23: =$B$9 -> 7666666.7 | D23: =B23-C23 -> 1.7333333e+08
A24: =A23+Increment -> 12 | B24: =D23 -> 1.7333333e+08 | C24: =$B$9 -> 7666666.7 | D24: =B24-C24 -> 1.6566667e+08
A25: =A24+Increment -> 13 | B25: =D24 -> 1.6566667e+08 | C25: =$B$9 -> 7666666.7 | D25: =B25-C25 -> 1.58e+08
A26: =A25+Increment -> 14 | B26: =D25 -> 1.58e+08 | C26: =$B$9 -> 7666666.7 | D26: =B26-C26 -> 1.5033333e+08
... A43: =A42+Increment -> 31 | B43: =D42 -> 27666667 | C43: =$B$9 -> 7666666.7 | D43: =B43-C43 -> 20000000
A45: EMPLOYMENT COST SCHEDULE
A46: Year | B46: Total Salary Cost | C46: Base Salary | D46: Employer Social Insurance | E46: Employee Deduction | F46: Payment to Employees | G46: Remittance to Government | H46: Monthly Payment to Employees | I46: Monthly Remittance to Government
A47: =Increment -> 1
A48: =A47+Increment -> 2 | B48: =Total_Crew_Costs -> 3500000 | C48: {=B48/(Increment+Employer_Social_Insurance_Rate)} -> 3070175.4 | D48: {=C48*Employer_Social_Insurance_Rate} -> 429824.56 | E48: {=C48*Employee_Deduction_Rate} -> 214912.28 | F48: =C48-E48 -> 2855263.2 | G48: =E48+D48 -> 644736.84 | H48: =F48/M_i_Y -> 237938.6 | I48: =G48/M_i_Y -> 53728.07
A49: =A48+Increment -> 3 | B49: =B48*(Increment+Inflation_Annual) -> 3552500 | C49: {=B49/(Increment+Employer_Social_Insurance_Rate)} -> 3116228.1 | D49: {=C49*Employer_Social_Insurance_Rate} -> 436271.93 | E49: {=C49*Employee_Deduction_Rate} -> 218135.96 | F49: =C49-E49 -> 2898092.1 | G49: =E49+D49 -> 654407.89 | H49: =F49/M_i_Y -> 241507.68 | I49: =G49/M_i_Y -> 54533.991
A50: =A49+Increment -> 4 | B50: =B49*(Increment+Inflation_Annual) -> 3605787.5 | C50: {=B50/(Increment+Employer_Social_Insurance_Rate)} -> 3162971.5 | D50: {=C50*Employer_Social_Insurance_Rate} -> 442816.01 | E50: {=C50*Employee_Deduction_Rate} -> 221408 | F50: =C50-E50 -> 2941563.5 | G50: =E50+D50 -> 664224.01 | H50: =F50/M_i_Y -> 245130.29 | I50: =G50/M_i_Y -> 55352.001
A51: =A50+Increment -> 5 | B51: =B50*(Increment+Inflation_Annual) -> 3659874.3 | C51: {=B51/(Increment+Employer_Social_Insurance_Rate)} -> 3210416.1 | D51: {=C51*Employer_Social_Insurance_Rate} -> 449458.25 | E51: {=C51*Employee_Deduction_Rate} -> 224729.12 | F51: =C51-E51 -> 2985686.9 | G51: =E51+D51 -> 674187.37 | H51: =F51/M_i_Y -> 248807.24 | I51: =G51/M_i_Y -> 56182.281
A52: =A51+Increment -> 6 | B52: =B51*(Increment+Inflation_Annual) -> 3714772.4 | C52: {=B52/(Increment+Employer_Social_Insurance_Rate)} -> 3258572.3 | D52: {=C52*Employer_Social_Insurance_Rate} -> 456200.12 | E52: {=C52*Employee_Deduction_Rate} -> 228100.06 | F52: =C52-E52 -> 3030472.2 | G52: =E52+D52 -> 684300.18 | H52: =F52/M_i_Y -> 252539.35 | I52: =G52/M_i_Y -> 57025.015
A53: =A52+Increment -> 7 | B53: =B52*(Increment+Inflation_Annual) -> 3770494 | C53: {=B53/(Increment+Employer_Social_Insurance_Rate)} -> 3307450.9 | D53: {=C53*Employer_Social_Insurance_Rate} -> 463043.12 | E53: {=C53*Employee_Deduction_Rate} -> 231521.56 | F53: =C53-E53 -> 3075929.3 | G53: =E53+D53 -> 694564.69 | H53: =F53/M_i_Y -> 256327.44 | I53: =G53/M_i_Y -> 57880.391
A54: =A53+Increment -> 8 | B54: =B53*(Increment+Inflation_Annual) -> 3827051.4 | C54: {=B54/(Increment+Employer_Social_Insurance_Rate)} -> 3357062.7 | D54: {=C54*Employer_Social_Insurance_Rate} -> 469988.77 | E54: {=C54*Employee_Deduction_Rate} -> 234994.39 | F54: =C54-E54 -> 3122068.3 | G54: =E54+D54 -> 704983.16 | H54: =F54/M_i_Y -> 260172.36 | I54: =G54/M_i_Y -> 58748.596
A55: =A54+Increment -> 9 | B55: =B54*(Increment+Inflation_Annual) -> 3884457.2 | C55: {=B55/(Increment+Employer_Social_Insurance_Rate)} -> 3407418.6 | D55: {=C55*Employer_Social_Insurance_Rate} -> 477038.6 | E55: {=C55*Employee_Deduction_Rate} -> 238519.3 | F55: =C55-E55 -> 3168899.3 | G55: =E55+D55 -> 715557.9 | H55: =F55/M_i_Y -> 264074.94 | I55: =G55/M_i_Y -> 59629.825
A56: =A55+Increment -> 10 | B56: =B55*(Increment+Inflation_Annual) -> 3942724.1 | C56: {=B56/(Increment+Employer_Social_Insurance_Rate)} -> 3458529.9 | D56: {=C56*Employer_Social_Insurance_Rate} -> 484194.18 | E56: {=C56*Employee_Deduction_Rate} -> 242097.09 | F56: =C56-E56 -> 3216432.8 | G56: =E56+D56 -> 726291.27 | H56: =F56/M_i_Y -> 268036.07 | I56: =G56/M_i_Y -> 60524.273
A57: =A56+Increment -> 11 | B57: =B56*(Increment+Inflation_Annual) -> 4001864.9 | C57: {=B57/(Increment+Employer_Social_Insurance_Rate)} -> 3510407.8 | D57: {=C57*Employer_Social_Insurance_Rate} -> 491457.09 | E57: {=C57*Employee_Deduction_Rate} -> 245728.55 | F57: =C57-E57 -> 3264679.3 | G57: =E57+D57 -> 737185.64 | H57: =F57/M_i_Y -> 272056.61 | I57: =G57/M_i_Y -> 61432.137
A58: =A57+Increment -> 12 | B58: =B57*(Increment+Inflation_Annual) -> 4061892.9 | C58: {=B58/(Increment+Employer_Social_Insurance_Rate)} -> 3563063.9 | D58: {=C58*Employer_Social_Insurance_Rate} -> 498828.95 | E58: {=C58*Employee_Deduction_Rate} -> 249414.48 | F58: =C58-E58 -> 3313649.5 | G58: =E58+D58 -> 748243.43 | H58: =F58/M_i_Y -> 276137.46 | I58: =G58/M_i_Y -> 62353.619
A59: =A58+Increment -> 13 | B59: =B58*(Increment+Inflation_Annual) -> 4122821.3 | C59: {=B59/(Increment+Employer_Social_Insurance_Rate)} -> 3616509.9 | D59: {=C59*Employer_Social_Insurance_Rate} -> 506311.39 | E59: {=C59*Employee_Deduction_Rate} -> 253155.69 | F59: =C59-E59 -> 3363354.2 | G59: =E59+D59 -> 759467.08 | H59: =F59/M_i_Y -> 280279.52 | I59: =G59/M_i_Y -> 63288.923
A60: =A59+Increment -> 14 | B60: =B59*(Increment+Inflation_Annual) -> 4184663.6 | C60: {=B60/(Increment+Employer_Social_Insurance_Rate)} -> 3670757.5 | D60: {=C60*Employer_Social_Insurance_Rate} -> 513906.06 | E60: {=C60*Employee_Deduction_Rate} -> 256953.03 | F60: =C60-E60 -> 3413804.5 | G60: =E60+D60 -> 770859.08 | H60: =F60/M_i_Y -> 284483.71 | I60: =G60/M_i_Y -> 64238.257
... A77: =A76+Increment -> 31 | B77: =B76*(Increment+Inflation_Annual) -> 5389931.8 | C77: {=B77/(Increment+Employer_Social_Insurance_Rate)} -> 4728010.3 | D77: {=C77*Employer_Social_Insurance_Rate} -> 661921.45 | E77: {=C77*Employee_Deduction_Rate} -> 330960.72 | F77: =C77-E77 -> 4397049.6 | G77: =E77+D77 -> 992882.17 | H77: =F77/M_i_Y -> 366420.8 | I77: =G77/M_i_Y -> 82740.181
A79: LNG REVENUE | F79: LNG PURCHASE PRICE
A80: Year | B80: LNG Demand ($/M3) | C80: Selling Price ($) | D80: Annual LNG Revenue ($) | F80: Year | G80: LNG Demand ($/M3) | H80: Purchas Price ($) | I80: Annual LNG COGS ($)
A81: =Increment -> 1 | F81: =Increment -> 1
A82: =A81+Increment -> 2 | B82: =Inputs!F59 -> 28330000 | C82: {=Sell_price_LNG*(Increment+Inflation_Annual)^(A82-First_Yr)} -> 28 | D82: =B82*C82 -> 793240000 | F82: =F81+Increment -> 2 | G82: =Inputs!F59 -> 28330000 | H82: {=Purch_price_LNG*(Increment+Inflation_Annual)^(F82-First_Yr)} -> 22 | I82: =G82*H82 -> 623260000
A83: =A82+Increment -> 3 | B83: =B82*(Demand_Increase+Increment) -> 28471650 | C83: {=Sell_price_LNG*(Increment+Inflation_Annual)^(A83-First_Yr)} -> 28.42 | D83: =B83*C83 -> 8.0916429e+08 | F83: =F82+Increment -> 3 | G83: =G82*(Demand_Increase+Increment) -> 28471650 | H83: {=Purch_price_LNG*(Increment+Inflation_Annual)^(F83-First_Yr)} -> 22.33 | I83: =G83*H83 -> 6.3577194e+08
A84: =A83+Increment -> 4 | B84: =B83*(Demand_Increase+Increment) -> 28614008 | C84: {=Sell_price_LNG*(Increment+Inflation_Annual)^(A84-First_Yr)} -> 28.8463 | D84: =B84*C84 -> 8.2540827e+08 | F84: =F83+Increment -> 4 | G84: =G83*(Demand_Increase+Increment) -> 28614008 | H84: {=Purch_price_LNG*(Increment+Inflation_Annual)^(F84-First_Yr)} -> 22.66495 | I84: =G84*H84 -> 6.4853507e+08
A85: =A84+Increment -> 5 | B85: =B84*(Demand_Increase+Increment) -> 28757078 | C85: {=Sell_price_LNG*(Increment+Inflation_Annual)^(A85-First_Yr)} -> 29.278994 | D85: =B85*C85 -> 8.4197834e+08 | F85: =F84+Increment -> 5 | G85: =G84*(Demand_Increase+Increment) -> 28757078 | H85: {=Purch_price_LNG*(Increment+Inflation_Annual)^(F85-First_Yr)} -> 23.004924 | I85: =G85*H85 -> 6.6155441e+08
A86: =A85+Increment -> 6 | B86: =B85*(Demand_Increase+Increment) -> 28900864 | C86: {=Sell_price_LNG*(Increment+Inflation_Annual)^(A86-First_Yr)} -> 29.718179 | D86: =B86*C86 -> 8.5888105e+08 | F86: =F85+Increment -> 6 | G86: =G85*(Demand_Increase+Increment) -> 28900864 | H86: {=Purch_price_LNG*(Increment+Inflation_Annual)^(F86-First_Yr)} -> 23.349998 | I86: =G86*H86 -> 6.7483511e+08
A87: =A86+Increment -> 7 | B87: =B86*(Demand_Increase+Increment) -> 29045368 | C87: {=Sell_price_LNG*(Increment+Inflation_Annual)^(A87-First_Yr)} -> 30.163952 | D87: =B87*C87 -> 8.7612309e+08 | F87: =F86+Increment -> 7 | G87: =G86*(Demand_Increase+Increment) -> 29045368 | H87: {=Purch_price_LNG*(Increment+Inflation_Annual)^(F87-First_Yr)} -> 23.700248 | I87: =G87*H87 -> 6.8838243e+08
A88: =A87+Increment -> 8 | B88: =B87*(Demand_Increase+Increment) -> 29190595 | C88: {=Sell_price_LNG*(Increment+Inflation_Annual)^(A88-First_Yr)} -> 30.616411 | D88: =B88*C88 -> 8.9371126e+08 | F88: =F87+Increment -> 8 | G88: =G87*(Demand_Increase+Increment) -> 29190595 | H88: {=Purch_price_LNG*(Increment+Inflation_Annual)^(F88-First_Yr)} -> 24.055752 | I88: =G88*H88 -> 7.022017e+08
A89: =A88+Increment -> 9 | B89: =B88*(Demand_Increase+Increment) -> 29336548 | C89: {=Sell_price_LNG*(Increment+Inflation_Annual)^(A89-First_Yr)} -> 31.075658 | D89: =B89*C89 -> 9.1165251e+08 | F89: =F88+Increment -> 9 | G89: =G88*(Demand_Increase+Increment) -> 29336548 | H89: {=Purch_price_LNG*(Increment+Inflation_Annual)^(F89-First_Yr)} -> 24.416588 | I89: =G89*H89 -> 7.162984e+08
A90: =A89+Increment -> 10 | B90: =B89*(Demand_Increase+Increment) -> 29483231 | C90: {=Sell_price_LNG*(Increment+Inflation_Annual)^(A90-First_Yr)} -> 31.541792 | D90: =B90*C90 -> 9.2995394e+08 | F90: =F89+Increment -> 10 | G90: =G89*(Demand_Increase+Increment) -> 29483231 | H90: {=Purch_price_LNG*(Increment+Inflation_Annual)^(F90-First_Yr)} -> 24.782837 | I90: =G90*H90 -> 7.3067809e+08
A91: =A90+Increment -> 11 | B91: =B90*(Demand_Increase+Increment) -> 29630647 | C91: {=Sell_price_LNG*(Increment+Inflation_Annual)^(A91-First_Yr)} -> 32.014919 | D91: =B91*C91 -> 9.4862276e+08 | F91: =F90+Increment -> 11 | G91: =G90*(Demand_Increase+Increment) -> 29630647 | H91: {=Purch_price_LNG*(Increment+Inflation_Annual)^(F91-First_Yr)} -> 25.154579 | I91: =G91*H91 -> 7.4534646e+08
A92: =A91+Increment -> 12 | B92: =B91*(Demand_Increase+Increment) -> 29778800 | C92: {=Sell_price_LNG*(Increment+Inflation_Annual)^(A92-First_Yr)} -> 32.495143 | D92: =B92*C92 -> 9.6766637e+08 | F92: =F91+Increment -> 12 | G92: =G91*(Demand_Increase+Increment) -> 29778800 | H92: {=Purch_price_LNG*(Increment+Inflation_Annual)^(F92-First_Yr)} -> 25.531898 | I92: =G92*H92 -> 7.6030929e+08
A93: =A92+Increment -> 13 | B93: =B92*(Demand_Increase+Increment) -> 29927694 | C93: {=Sell_price_LNG*(Increment+Inflation_Annual)^(A93-First_Yr)} -> 32.98257 | D93: =B93*C93 -> 9.8709227e+08 | F93: =F92+Increment -> 13 | G93: =G92*(Demand_Increase+Increment) -> 29927694 | H93: {=Purch_price_LNG*(Increment+Inflation_Annual)^(F93-First_Yr)} -> 25.914877 | I93: =G93*H93 -> 7.755725e+08
A94: =A93+Increment -> 14 | B94: =B93*(Demand_Increase+Increment) -> 30077332 | C94: {=Sell_price_LNG*(Increment+Inflation_Annual)^(A94-First_Yr)} -> 33.477309 | D94: =B94*C94 -> 1.0069081e+09 | F94: =F93+Increment -> 14 | G94: =G93*(Demand_Increase+Increment) -> 30077332 | H94: {=Purch_price_LNG*(Increment+Inflation_Annual)^(F94-First_Yr)} -> 26.3036 | I94: =G94*H94 -> 7.9114211e+08
... A111: =A110+Increment -> 31 | B111: =B110*(Demand_Increase+Increment) -> 32738770 | C111: {=Sell_price_LNG*(Increment+Inflation_Annual)^(A111-First_Yr)} -> 43.119454 | D111: =B111*C111 -> 1.4116779e+09 | F111: =F110+Increment -> 31 | G111: =G110*(Demand_Increase+Increment) -> 32738770 | H111: {=Purch_price_LNG*(Increment+Inflation_Annual)^(F111-First_Yr)} -> 33.879571 | I111: =G111*H111 -> 1.1091755e+09
A113: PORT FEES | F113: HFO COST
A114: Year | B114: Port Fees Cost Per Trip | C114: Trips Required | D114: Annual Port Fees ($) | F114: Year | G114: HFO Cost Per Trip ($) | H114: Trips Required | I114: Annual HFO Costs ($)
A115: =Increment -> 1 | F115: =Increment -> 1
A116: =A115+Increment -> 2 | B116: {=Port_Fees*(Increment+Inflation_Annual)^(A116-First_Yr)} -> 220000 | C116: {=ROUNDUP(B82/LNG_Tanker_Cap,0)} -> 109 | D116: =B116*C116 -> 23980000 | F116: =F115+Increment -> 2 | G116: {=Heavy_Fuel_Oil*Tons_Req_a_Trip*(Increment+Inflation_Annual)^(F116-First_Yr)} -> 9120 | H116: {=ROUNDUP(G82/LNG_Tanker_Cap,0)} -> 109 | I116: =G116*H116 -> 994080
A117: =A116+Increment -> 3 | B117: {=Port_Fees*(Increment+Inflation_Annual)^(A117-First_Yr)} -> 223300 | C117: {=ROUNDUP(B83/LNG_Tanker_Cap,0)} -> 110 | D117: =B117*C117 -> 24563000 | F117: =F116+Increment -> 3 | G117: {=Heavy_Fuel_Oil*Tons_Req_a_Trip*(Increment+Inflation_Annual)^(F117-First_Yr)} -> 9256.8 | H117: {=ROUNDUP(G83/LNG_Tanker_Cap,0)} -> 110 | I117: =G117*H117 -> 1018248
A118: =A117+Increment -> 4 | B118: {=Port_Fees*(Increment+Inflation_Annual)^(A118-First_Yr)} -> 226649.5 | C118: {=ROUNDUP(B84/LNG_Tanker_Cap,0)} -> 111 | D118: =B118*C118 -> 25158094 | F118: =F117+Increment -> 4 | G118: {=Heavy_Fuel_Oil*Tons_Req_a_Trip*(Increment+Inflation_Annual)^(F118-First_Yr)} -> 9395.652 | H118: {=ROUNDUP(G84/LNG_Tanker_Cap,0)} -> 111 | I118: =G118*H118 -> 1042917.4
A119: =A118+Increment -> 5 | B119: {=Port_Fees*(Increment+Inflation_Annual)^(A119-First_Yr)} -> 230049.24 | C119: {=ROUNDUP(B85/LNG_Tanker_Cap,0)} -> 111 | D119: =B119*C119 -> 25535466 | F119: =F118+Increment -> 5 | G119: {=Heavy_Fuel_Oil*Tons_Req_a_Trip*(Increment+Inflation_Annual)^(F119-First_Yr)} -> 9536.5868 | H119: {=ROUNDUP(G85/LNG_Tanker_Cap,0)} -> 111 | I119: =G119*H119 -> 1058561.1
A120: =A119+Increment -> 6 | B120: {=Port_Fees*(Increment+Inflation_Annual)^(A120-First_Yr)} -> 233499.98 | C120: {=ROUNDUP(B86/LNG_Tanker_Cap,0)} -> 112 | D120: =B120*C120 -> 26151998 | F120: =F119+Increment -> 6 | G120: {=Heavy_Fuel_Oil*Tons_Req_a_Trip*(Increment+Inflation_Annual)^(F120-First_Yr)} -> 9679.6356 | H120: {=ROUNDUP(G86/LNG_Tanker_Cap,0)} -> 112 | I120: =G120*H120 -> 1084119.2
A121: =A120+Increment -> 7 | B121: {=Port_Fees*(Increment+Inflation_Annual)^(A121-First_Yr)} -> 237002.48 | C121: {=ROUNDUP(B87/LNG_Tanker_Cap,0)} -> 112 | D121: =B121*C121 -> 26544278 | F121: =F120+Increment -> 7 | G121: {=Heavy_Fuel_Oil*Tons_Req_a_Trip*(Increment+Inflation_Annual)^(F121-First_Yr)} -> 9824.8301 | H121: {=ROUNDUP(G87/LNG_Tanker_Cap,0)} -> 112 | I121: =G121*H121 -> 1100381
A122: =A121+Increment -> 8 | B122: {=Port_Fees*(Increment+Inflation_Annual)^(A122-First_Yr)} -> 240557.52 | C122: {=ROUNDUP(B88/LNG_Tanker_Cap,0)} -> 113 | D122: =B122*C122 -> 27183000 | F122: =F121+Increment -> 8 | G122: {=Heavy_Fuel_Oil*Tons_Req_a_Trip*(Increment+Inflation_Annual)^(F122-First_Yr)} -> 9972.2026 | H122: {=ROUNDUP(G88/LNG_Tanker_Cap,0)} -> 113 | I122: =G122*H122 -> 1126858.9
A123: =A122+Increment -> 9 | B123: {=Port_Fees*(Increment+Inflation_Annual)^(A123-First_Yr)} -> 244165.88 | C123: {=ROUNDUP(B89/LNG_Tanker_Cap,0)} -> 113 | D123: =B123*C123 -> 27590745 | F123: =F122+Increment -> 9 | G123: {=Heavy_Fuel_Oil*Tons_Req_a_Trip*(Increment+Inflation_Annual)^(F123-First_Yr)} -> 10121.786 | H123: {=ROUNDUP(G89/LNG_Tanker_Cap,0)} -> 113 | I123: =G123*H123 -> 1143761.8
A124: =A123+Increment -> 10 | B124: {=Port_Fees*(Increment+Inflation_Annual)^(A124-First_Yr)} -> 247828.37 | C124: {=ROUNDUP(B90/LNG_Tanker_Cap,0)} -> 114 | D124: =B124*C124 -> 28252434 | F124: =F123+Increment -> 10 | G124: {=Heavy_Fuel_Oil*Tons_Req_a_Trip*(Increment+Inflation_Annual)^(F124-First_Yr)} -> 10273.612 | H124: {=ROUNDUP(G90/LNG_Tanker_Cap,0)} -> 114 | I124: =G124*H124 -> 1171191.8
A125: =A124+Increment -> 11 | B125: {=Port_Fees*(Increment+Inflation_Annual)^(A125-First_Yr)} -> 251545.79 | C125: {=ROUNDUP(B91/LNG_Tanker_Cap,0)} -> 114 | D125: =B125*C125 -> 28676221 | F125: =F124+Increment -> 11 | G125: {=Heavy_Fuel_Oil*Tons_Req_a_Trip*(Increment+Inflation_Annual)^(F125-First_Yr)} -> 10427.717 | H125: {=ROUNDUP(G91/LNG_Tanker_Cap,0)} -> 114 | I125: =G125*H125 -> 1188759.7
A126: =A125+Increment -> 12 | B126: {=Port_Fees*(Increment+Inflation_Annual)^(A126-First_Yr)} -> 255318.98 | C126: {=ROUNDUP(B92/LNG_Tanker_Cap,0)} -> 115 | D126: =B126*C126 -> 29361683 | F126: =F125+Increment -> 12 | G126: {=Heavy_Fuel_Oil*Tons_Req_a_Trip*(Increment+Inflation_Annual)^(F126-First_Yr)} -> 10584.132 | H126: {=ROUNDUP(G92/LNG_Tanker_Cap,0)} -> 115 | I126: =G126*H126 -> 1217175.2
A127: =A126+Increment -> 13 | B127: {=Port_Fees*(Increment+Inflation_Annual)^(A127-First_Yr)} -> 259148.77 | C127: {=ROUNDUP(B93/LNG_Tanker_Cap,0)} -> 116 | D127: =B127*C127 -> 30061257 | F127: =F126+Increment -> 13 | G127: {=Heavy_Fuel_Oil*Tons_Req_a_Trip*(Increment+Inflation_Annual)^(F127-First_Yr)} -> 10742.894 | H127: {=ROUNDUP(G93/LNG_Tanker_Cap,0)} -> 116 | I127: =G127*H127 -> 1246175.7
... A145: =A144+Increment -> 31 | B145: {=Port_Fees*(Increment+Inflation_Annual)^(A145-First_Yr)} -> 338795.71 | C145: {=ROUNDUP(B111/LNG_Tanker_Cap,0)} -> 126 | D145: =B145*C145 -> 42688260 | F145: =F144+Increment -> 31 | G145: {=Heavy_Fuel_Oil*Tons_Req_a_Trip*(Increment+Inflation_Annual)^(F145-First_Yr)} -> 14044.622 | H145: {=ROUNDUP(G111/LNG_Tanker_Cap,0)} -> 126 | I145: =G145*H145 -> 1769622.4
A147: SHIPPING OPERATING EXPENSE
A148: Year | B148: Port Fees Cost Per Trip ($) | C148: Trips Required | D148: Annual Port Fees ($)
A149: =Increment -> 1
A150: =A149+Increment -> 2 | B150: {=Operating_Exp*(Increment+Inflation_Annual)^(A150-First_Yr)} -> 40000 | C150: {=ROUNDUP(B82/LNG_Tanker_Cap,0)} -> 109 | D150: =B150*C150 -> 4360000
A151: =A150+Increment -> 3 | B151: {=Operating_Exp*(Increment+Inflation_Annual)^(A151-First_Yr)} -> 40600 | C151: {=ROUNDUP(B83/LNG_Tanker_Cap,0)} -> 110 | D151: =B151*C151 -> 4466000
A152: =A151+Increment -> 4 | B152: {=Operating_Exp*(Increment+Inflation_Annual)^(A152-First_Yr)} -> 41209 | C152: {=ROUNDUP(B84/LNG_Tanker_Cap,0)} -> 111 | D152: =B152*C152 -> 4574199
A153: =A152+Increment -> 5 | B153: {=Operating_Exp*(Increment+Inflation_Annual)^(A153-First_Yr)} -> 41827.135 | C153: {=ROUNDUP(B85/LNG_Tanker_Cap,0)} -> 111 | D153: =B153*C153 -> 4642812
A154: =A153+Increment -> 6 | B154: {=Operating_Exp*(Increment+Inflation_Annual)^(A154-First_Yr)} -> 42454.542 | C154: {=ROUNDUP(B86/LNG_Tanker_Cap,0)} -> 112 | D154: =B154*C154 -> 4754908.7
A155: =A154+Increment -> 7 | B155: {=Operating_Exp*(Increment+Inflation_Annual)^(A155-First_Yr)} -> 43091.36 | C155: {=ROUNDUP(B87/LNG_Tanker_Cap,0)} -> 112 | D155: =B155*C155 -> 4826232.3
A156: =A155+Increment -> 8 | B156: {=Operating_Exp*(Increment+Inflation_Annual)^(A156-First_Yr)} -> 43737.731 | C156: {=ROUNDUP(B88/LNG_Tanker_Cap,0)} -> 113 | D156: =B156*C156 -> 4942363.6
A157: =A156+Increment -> 9 | B157: {=Operating_Exp*(Increment+Inflation_Annual)^(A157-First_Yr)} -> 44393.797 | C157: {=ROUNDUP(B89/LNG_Tanker_Cap,0)} -> 113 | D157: =B157*C157 -> 5016499
A158: =A157+Increment -> 10 | B158: {=Operating_Exp*(Increment+Inflation_Annual)^(A158-First_Yr)} -> 45059.703 | C158: {=ROUNDUP(B90/LNG_Tanker_Cap,0)} -> 114 | D158: =B158*C158 -> 5136806.2
A159: =A158+Increment -> 11 | B159: {=Operating_Exp*(Increment+Inflation_Annual)^(A159-First_Yr)} -> 45735.599 | C159: {=ROUNDUP(B91/LNG_Tanker_Cap,0)} -> 114 | D159: =B159*C159 -> 5213858.3
A160: =A159+Increment -> 12 | B160: {=Operating_Exp*(Increment+Inflation_Annual)^(A160-First_Yr)} -> 46421.633 | C160: {=ROUNDUP(B92/LNG_Tanker_Cap,0)} -> 115 | D160: =B160*C160 -> 5338487.8
A161: =A160+Increment -> 13 | B161: {=Operating_Exp*(Increment+Inflation_Annual)^(A161-First_Yr)} -> 47117.957 | C161: {=ROUNDUP(B93/LNG_Tanker_Cap,0)} -> 116 | D161: =B161*C161 -> 5465683.1
... A179: =A178+Increment -> 31 | B179: {=Operating_Exp*(Increment+Inflation_Annual)^(A179-First_Yr)} -> 61599.221 | C179: {=ROUNDUP(B111/LNG_Tanker_Cap,0)} -> 126 | D179: =B179*C179 -> 7761501.8
A181: FINANCE SCHEDULE
A182: Annual Payment | C182: {=PMT(Discount_Rate,Total_Years,-B186,0,0)} -> 15372204
H183: Monthly Interest Expense - Y1
A184: Year | B184: Principal | C184: Interest | D184: Payment | E184: Amortization | F184: Ending balance | H184: Month | I184: Outstanding balance | J184: Interest expense
A185: =Increment -> 1 | B185: =Building_Cost_Tanker+Min_Cash_Balance -> 260000000 | C185: =J197 -> 5816666.7 | F185: =B185+C185 -> 2.6581667e+08 | H185: January | I185: =Building_Cost_Tanker/M_i_Y+Min_Cash_Balance -> 30833333 | J185: =I185*Discount_Rate/M_i_Y -> 102777.78
A186: =A185+Increment -> 2 | B186: =F185 -> 2.6581667e+08 | C186: =B186*Discount_Rate -> 10632667 | D186: =$C$182 -> 15372204 | E186: =D186-C186 -> 4739537.5 | F186: =B186-E186 -> 2.6107713e+08 | H186: February | I186: =Building_Cost_Tanker/M_i_Y+I185 -> 51666667 | J186: =I186*Discount_Rate/M_i_Y -> 172222.22
A187: =A186+Increment -> 3 | B187: =F186 -> 2.6107713e+08 | C187: =B187*Discount_Rate -> 10443085 | D187: =$C$182 -> 15372204 | E187: =D187-C187 -> 4929119 | F187: =B187-E187 -> 2.5614801e+08 | H187: March | I187: =Building_Cost_Tanker/M_i_Y+I186 -> 72500000 | J187: =I187*Discount_Rate/M_i_Y -> 241666.67
A188: =A187+Increment -> 4 | B188: =F187 -> 2.5614801e+08 | C188: =B188*Discount_Rate -> 10245920 | D188: =$C$182 -> 15372204 | E188: =D188-C188 -> 5126283.8 | F188: =B188-E188 -> 2.5102173e+08 | H188: April | I188: =Building_Cost_Tanker/M_i_Y+I187 -> 93333333 | J188: =I188*Discount_Rate/M_i_Y -> 311111.11
A189: =A188+Increment -> 5 | B189: =F188 -> 2.5102173e+08 | C189: =B189*Discount_Rate -> 10040869 | D189: =$C$182 -> 15372204 | E189: =D189-C189 -> 5331335.1 | F189: =B189-E189 -> 2.4569039e+08 | H189: May | I189: =Building_Cost_Tanker/M_i_Y+I188 -> 1.1416667e+08 | J189: =I189*Discount_Rate/M_i_Y -> 380555.56
...

Sheet Cash Budget
A1: QATAR ENERGY
A2: CASH BUDGET
A3: FOR THE FINANCIAL YEARS ENDED DECEMBER 31
B5: Year 1 | N5: Year 1 Total | O5: Year 2 | AA5: Year 2 Total | AB5: Year 3 | AC5: Year 4 | AD5: Year 5
B6: January | C6: February | D6: March | E6: April | F6: May | G6: June | H6: July | I6: August | J6: September | K6: October | L6: November | M6: December | O6: January | P6: February | Q6: March | R6: April | S6: May | T6: June | U6: July | V6: August | W6: September | X6: October | Y6: November | Z6: December
A7: Opening Cash | B7: {=Nil} -> 0 | C7: =B33 -> 833333.33 | D7: =C33 -> 1666666.7 | E7: =D33 -> 2500000 | F7: =E33 -> 3333333.3 | G7: =F33 -> 4166666.7 | H7: =G33 -> 5000000 | I7: =H33 -> 5833333.3 | J7: =I33 -> 6666666.7 | ... M7: =L33 -> 9166666.7 | N7: =B7 -> 0 | O7: =M33 -> 10000000 | P7: =O33 -> 70031911 | Q7: =P33 -> 72666805 | R7: =Q33 -> 85966655 | S7: =R33 -> 92402152 | T7: =S33 -> 1.0271581e+08 | U7: =T33 -> 1.0915131e+08 | V7: =U33 -> 1.1946497e+08 | W7: =V33 -> 1.2807224e+08 | ... Z7: =Y33 -> 1.512569e+08 | AA7: =O7 -> 10000000 | AB7: =Z33 -> 1.4619836e+08 | AC7: =AB33 -> 2.3102332e+08 | AD7: =AC33 -> 3.1764408e+08
A8: Bank Loan Drawn-out | B8: ='Tanker Schedule'!$J$201 -> 21666667 | C8: ='Tanker Schedule'!$J$201 -> 21666667 | D8: ='Tanker Schedule'!$J$201 -> 21666667 | E8: ='Tanker Schedule'!$J$201 -> 21666667 | F8: ='Tanker Schedule'!$J$201 -> 21666667 | G8: ='Tanker Schedule'!$J$201 -> 21666667 | H8: ='Tanker Schedule'!$J$201 -> 21666667 | I8: ='Tanker Schedule'!$J$201 -> 21666667 | ... M8: ='Tanker Schedule'!$J$201 -> 21666667 | N8: =SUM(B8:M8) -> 2.6e+08 | O8: {=Nil} -> 0 | P8: {=Nil} -> 0 | Q8: {=Nil} -> 0 | R8: {=Nil} -> 0 | S8: {=Nil} -> 0 | T8: {=Nil} -> 0 | U8: {=Nil} -> 0 | V8: {=Nil} -> 0 | ... Z8: {=Nil} -> 0 | AA8: =SUM(O8:Z8) -> 0 | AB8: {=Nil} -> 0 | AC8: {=Nil} -> 0 | AD8: {=Nil} -> 0
A9: Revenue | B9: {=Nil} -> 0 | C9: {=Nil} -> 0 | D9: {=Nil} -> 0 | E9: {=Nil} -> 0 | F9: {=Nil} -> 0 | G9: {=Nil} -> 0 | H9: {=Nil} -> 0 | I9: {=Nil} -> 0 | ... M9: {=Nil} -> 0 | N9: =SUM(B9:M9) -> 0 | O9: {='Tanker Schedule'!D82/D_i_Y*(Days_Jan-Increment)} -> 65153183 | P9: {='Tanker Schedule'!D82/D_i_Y*Days_Feb} -> 61352580 | Q9: {='Tanker Schedule'!D82/D_i_Y*Days_Mar} -> 67324956 | R9: {='Tanker Schedule'!D82/D_i_Y*Days_Apr} -> 65153183 | S9: {='Tanker Schedule'!D82/D_i_Y*Days_May} -> 67324956 | T9: {='Tanker Schedule'!D82/D_i_Y*Days_Jun} -> 65153183 | U9: {='Tanker Schedule'!D82/D_i_Y*Days_Jul} -> 67324956 | V9: {='Tanker Schedule'!D82/D_i_Y*Days_Aug} -> 67324956 | W9: {='Tanker Schedule'!D82/D_i_Y*Days_Sept} -> 65153183 | X9: {='Tanker Schedule'!D82/D_i_Y*Days_Oct} -> 67324956 | Y9: {='Tanker Schedule'!D82/D_i_Y*Days_Nov} -> 65153183 | Z9: {='Tanker Schedule'!D82/D_i_Y*Days_Dec} -> 67324956 | AA9: =SUM(O9:Z9) -> 7.9106823e+08 | AB9: =('Tanker Schedule'!D82/D_i_Y)+('Tanker Schedule'!D83)-('Tanker Schedule'!D83/D_i_Y) -> 8.0912069e+08 | AC9: =('Tanker Schedule'!D83/D_i_Y)+('Tanker Schedule'!D84)-('Tanker Schedule'!D84/D_i_Y) -> 8.2536379e+08 | AD9: =('Tanker Schedule'!D84/D_i_Y)+('Tanker Schedule'!D85)-('Tanker Schedule'!D85/D_i_Y) -> 8.4193297e+08
A10: Total Cash Inflows: | B10: =SUM(B8:B9) -> 21666667 | C10: =SUM(C8:C9) -> 21666667 | D10: =SUM(D8:D9) -> 21666667 | E10: =SUM(E8:E9) -> 21666667 | F10: =SUM(F8:F9) -> 21666667 | G10: =SUM(G8:G9) -> 21666667 | H10: =SUM(H8:H9) -> 21666667 | I10: =SUM(I8:I9) -> 21666667 | ... M10: =SUM(M8:M9) -> 21666667 | N10: =SUM(B10:M10) -> 2.6e+08 | O10: =SUM(O8:O9) -> 65153183 | P10: =SUM(P8:P9) -> 61352580 | Q10: =SUM(Q8:Q9) -> 67324956 | R10: =SUM(R8:R9) -> 65153183 | S10: =SUM(S8:S9) -> 67324956 | T10: =SUM(T8:T9) -> 65153183 | U10: =SUM(U8:U9) -> 67324956 | V10: =SUM(V8:V9) -> 67324956 | ... AD10: =SUM(AD8:AD9) -> 8.4193297e+08
A12: Initial Capital Expenditures:
A13: Tanker Building Cost | B13: =Building_Cost_Tanker/M_i_Y -> 20833333 | C13: =Building_Cost_Tanker/M_i_Y -> 20833333 | D13: =Building_Cost_Tanker/M_i_Y -> 20833333 | E13: =Building_Cost_Tanker/M_i_Y -> 20833333 | F13: =Building_Cost_Tanker/M_i_Y -> 20833333 | G13: =Building_Cost_Tanker/M_i_Y -> 20833333 | H13: =Building_Cost_Tanker/M_i_Y -> 20833333 | I13: =Building_Cost_Tanker/M_i_Y -> 20833333 | ... M13: =Building_Cost_Tanker/M_i_Y -> 20833333 | N13: =SUM(B13:M13) -> 2.5e+08 | O13: {=Nil} -> 0 | P13: {=Nil} -> 0 | Q13: {=Nil} -> 0 | R13: {=Nil} -> 0 | S13: {=Nil} -> 0 | T13: {=Nil} -> 0 | U13: {=Nil} -> 0 | V13: {=Nil} -> 0 | ... Z13: {=Nil} -> 0 | AA13: =SUM(O13:Z13) -> 0 | AB13: {=Nil} -> 0 | AC13: {=Nil} -> 0 | AD13: {=Nil} -> 0
A14: Trip Costs: | AA14: =SUM(O14:Z14) -> 0
A15: Port fees | B15: {=Nil} -> 0 | C15: {=Nil} -> 0 | D15: {=Nil} -> 0 | E15: {=Nil} -> 0 | F15: {=Nil} -> 0 | G15: {=Nil} -> 0 | H15: {=Nil} -> 0 | I15: {=Nil} -> 0 | ... M15: {=Nil} -> 0 | N15: =SUM(B15:M15) -> 0 | O15: {=Nil} -> 0 | P15: ='Tanker Schedule'!$D$116/M_i_Y -> 1998333.3 | Q15: ='Tanker Schedule'!$D$116/M_i_Y -> 1998333.3 | R15: ='Tanker Schedule'!$D$116/M_i_Y -> 1998333.3 | S15: ='Tanker Schedule'!$D$116/M_i_Y -> 1998333.3 | T15: ='Tanker Schedule'!$D$116/M_i_Y -> 1998333.3 | U15: ='Tanker Schedule'!$D$116/M_i_Y -> 1998333.3 | V15: ='Tanker Schedule'!$D$116/M_i_Y -> 1998333.3 | W15: ='Tanker Schedule'!$D$116/M_i_Y -> 1998333.3 | ... Z15: ='Tanker Schedule'!$D$116/M_i_Y -> 1998333.3 | AA15: =SUM(O15:Z15) -> 21981667 | AB15: =('Tanker Schedule'!D116/M_i_Y)+('Tanker Schedule'!D117*(M_i_Y-Increment)/M_i_Y) -> 24514417 | AC15: =('Tanker Schedule'!D117/M_i_Y)+('Tanker Schedule'!D118*(M_i_Y-Increment)/M_i_Y) -> 25108503 | AD15: =('Tanker Schedule'!D118/M_i_Y)+('Tanker Schedule'!D119*(M_i_Y-Increment)/M_i_Y) -> 25504018
A16: Heavy Fuel Oil | B16: {=Nil} -> 0 | C16: {=Nil} -> 0 | D16: {=Nil} -> 0 | E16: {=Nil} -> 0 | F16: {=Nil} -> 0 | G16: {=Nil} -> 0 | H16: {=Nil} -> 0 | I16: {=Nil} -> 0 | ... M16: {=Nil} -> 0 | N16: =SUM(B16:M16) -> 0 | O16: {=Nil} -> 0 | P16: ='Tanker Schedule'!$I$116/M_i_Y -> 82840 | Q16: ='Tanker Schedule'!$I$116/M_i_Y -> 82840 | R16: ='Tanker Schedule'!$I$116/M_i_Y -> 82840 | S16: ='Tanker Schedule'!$I$116/M_i_Y -> 82840 | T16: ='Tanker Schedule'!$I$116/M_i_Y -> 82840 | U16: ='Tanker Schedule'!$I$116/M_i_Y -> 82840 | V16: ='Tanker Schedule'!$I$116/M_i_Y -> 82840 | W16: ='Tanker Schedule'!$I$116/M_i_Y -> 82840 | ... Z16: ='Tanker Schedule'!$I$116/M_i_Y -> 82840 | AA16: =SUM(O16:Z16) -> 911240 | AB16: =('Tanker Schedule'!I116/M_i_Y)+('Tanker Schedule'!I117*(M_i_Y-Increment)/M_i_Y) -> 1016234 | AC16: =('Tanker Schedule'!I117/M_i_Y)+('Tanker Schedule'!I118*(M_i_Y-Increment)/M_i_Y) -> 1040861.6 | AD16: =('Tanker Schedule'!I118/M_i_Y)+('Tanker Schedule'!I119*(M_i_Y-Increment)/M_i_Y) -> 1057257.5
A17: Shipping Operating Expense | B17: {=Nil} -> 0 | C17: {=Nil} -> 0 | D17: {=Nil} -> 0 | E17: {=Nil} -> 0 | F17: {=Nil} -> 0 | G17: {=Nil} -> 0 | H17: {=Nil} -> 0 | I17: {=Nil} -> 0 | ... M17: {=Nil} -> 0 | N17: =SUM(B17:M17) -> 0 | O17: {=Nil} -> 0 | P17: ='Tanker Schedule'!$D$150/M_i_Y -> 363333.33 | Q17: ='Tanker Schedule'!$D$150/M_i_Y -> 363333.33 | R17: ='Tanker Schedule'!$D$150/M_i_Y -> 363333.33 | S17: ='Tanker Schedule'!$D$150/M_i_Y -> 363333.33 | T17: ='Tanker Schedule'!$D$150/M_i_Y -> 363333.33 | U17: ='Tanker Schedule'!$D$150/M_i_Y -> 363333.33 | V17: ='Tanker Schedule'!$D$150/M_i_Y -> 363333.33 | W17: ='Tanker Schedule'!$D$150/M_i_Y -> 363333.33 | ... Z17: ='Tanker Schedule'!$D$150/M_i_Y -> 363333.33 | AA17: =SUM(O17:Z17) -> 3996666.7 | AB17: =('Tanker Schedule'!D150/M_i_Y)+('Tanker Schedule'!D151*(M_i_Y-Increment)/M_i_Y) -> 4457166.7 | AC17: =('Tanker Schedule'!D151/M_i_Y)+('Tanker Schedule'!D152*(M_i_Y-Increment)/M_i_Y) -> 4565182.4 | AD17: =('Tanker Schedule'!D152/M_i_Y)+('Tanker Schedule'!D153*(M_i_Y-Increment)/M_i_Y) -> 4637094.2
A18: LNG Purchase | B18: {=Nil} -> 0 | C18: {=Nil} -> 0 | D18: {=Nil} -> 0 | E18: {=Nil} -> 0 | F18: {=Nil} -> 0 | G18: {=Nil} -> 0 | H18: {=Nil} -> 0 | I18: {=Nil} -> 0 | ... M18: {=Nil} -> 0 | N18: =SUM(B18:M18) -> 0 | O18: {=Nil} -> 0 | P18: {='Tanker Schedule'!$I$82/D_i_Y*Days_Jan} -> 52898179 | Q18: {='Tanker Schedule'!$I$82/D_i_Y*Days_Feb} -> 48205599 | R18: {='Tanker Schedule'!$I$82/D_i_Y*Days_Mar} -> 52898179 | S18: {='Tanker Schedule'!$I$82/D_i_Y*Days_Apr} -> 51191786 | T18: {='Tanker Schedule'!$I$82/D_i_Y*Days_May} -> 52898179 | U18: {='Tanker Schedule'!$I$82/D_i_Y*Days_Jun} -> 51191786 | V18: {='Tanker Schedule'!$I$82/D_i_Y*Days_Jul} -> 52898179 | W18: {='Tanker Schedule'!$I$82/D_i_Y*Days_Aug} -> 52898179 | X18: {='Tanker Schedule'!$I$82/D_i_Y*Days_Sept} -> 51191786 | Y18: {='Tanker Schedule'!$I$82/D_i_Y*Days_Oct} -> 52898179 | Z18: {='Tanker Schedule'!$I$82/D_i_Y*Days_Nov} -> 51191786 | AA18: =SUM(O18:Z18) -> 5.7036182e+08 | AB18: {=('Tanker Schedule'!$I$82/D_i_Y*Days_Dec)+('Tanker Schedule'!I83*(D_i_Y-Days_Dec)/D_i_Y)} -> 6.3471001e+08 | AC18: {=('Tanker Schedule'!I83/D_i_Y*Days_Dec)+('Tanker Schedule'!I84*(D_i_Y-Days_Dec)/D_i_Y)} -> 6.4745182e+08 | AD18: {=('Tanker Schedule'!I84/D_i_Y*Days_Dec)+('Tanker Schedule'!I85*(D_i_Y-Days_Dec)/D_i_Y)} -> 6.6044941e+08
A19: Operating Costs:
A20: Insurance | B20: {=Nil} -> 0 | C20: {=Nil} -> 0 | D20: {=Nil} -> 0 | E20: {=Nil} -> 0 | F20: {=Nil} -> 0 | G20: {=Nil} -> 0 | H20: {=Nil} -> 0 | I20: {=Nil} -> 0 | ... M20: {=Nil} -> 0 | N20: =SUM(B20:M20) -> 0 | O20: =Insurance_Tanker -> 1800000 | P20: {=Nil} -> 0 | Q20: {=Nil} -> 0 | R20: {=Nil} -> 0 | S20: {=Nil} -> 0 | T20: {=Nil} -> 0 | U20: {=Nil} -> 0 | V20: {=Nil} -> 0 | W20: {=Nil} -> 0 | ... Z20: {=Nil} -> 0 | AA20: =SUM(O20:Z20) -> 1800000 | AB20: =AA20*(Increment+Inflation_Annual) -> 1827000 | AC20: =AB20*(Increment+Inflation_Annual) -> 1854405 | AD20: =AC20*(Increment+Inflation_Annual) -> 1882221.1
A21: Payroll - Payment to Employees | B21: {=Nil} -> 0 | C21: {=Nil} -> 0 | D21: {=Nil} -> 0 | E21: {=Nil} -> 0 | F21: {=Nil} -> 0 | G21: {=Nil} -> 0 | H21: {=Nil} -> 0 | I21: {=Nil} -> 0 | ... M21: {=Nil} -> 0 | N21: =SUM(B21:M21) -> 0 | O21: ='Tanker Schedule'!$H$48 -> 237938.6 | P21: ='Tanker Schedule'!$H$48 -> 237938.6 | Q21: ='Tanker Schedule'!$H$48 -> 237938.6 | R21: ='Tanker Schedule'!$H$48 -> 237938.6 | S21: ='Tanker Schedule'!$H$48 -> 237938.6 | T21: ='Tanker Schedule'!$H$48 -> 237938.6 | U21: ='Tanker Schedule'!$H$48 -> 237938.6 | V21: ='Tanker Schedule'!$H$48 -> 237938.6 | ... Z21: ='Tanker Schedule'!$H$48 -> 237938.6 | AA21: =SUM(O21:Z21) -> 2855263.2 | AB21: ='Tanker Schedule'!F49 -> 2898092.1 | AC21: ='Tanker Schedule'!F50 -> 2941563.5 | AD21: ='Tanker Schedule'!F51 -> 2985686.9
A22: Payroll - Remittance to Government | O22: {=Nil} -> 0 | P22: ='Tanker Schedule'!$I$48 -> 53728.07 | Q22: ='Tanker Schedule'!$I$48 -> 53728.07 | R22: ='Tanker Schedule'!$I$48 -> 53728.07 | S22: ='Tanker Schedule'!$I$48 -> 53728.07 | T22: ='Tanker Schedule'!$I$48 -> 53728.07 | U22: ='Tanker Schedule'!$I$48 -> 53728.07 | V22: ='Tanker Schedule'!$I$48 -> 53728.07 | W22: ='Tanker Schedule'!$I$48 -> 53728.07 | ... Z22: ='Tanker Schedule'!$I$48 -> 53728.07 | AA22: =SUM(O22:Z22) -> 591008.77 | AB22: ='Tanker Schedule'!I48+('Tanker Schedule'!I49*(M_i_Y-Increment)) -> 653601.97 | AC22: ='Tanker Schedule'!I49+('Tanker Schedule'!I50*(M_i_Y-Increment)) -> 663406 | AD22: ='Tanker Schedule'!I50+('Tanker Schedule'!I51*(M_i_Y-Increment)) -> 673357.09
A23: Maintenance and Engineering | B23: {=Nil} -> 0 | C23: {=Nil} -> 0 | D23: {=Nil} -> 0 | E23: {=Nil} -> 0 | F23: {=Nil} -> 0 | G23: {=Nil} -> 0 | H23: {=Nil} -> 0 | I23: {=Nil} -> 0 | ... M23: {=Nil} -> 0 | N23: =SUM(B23:M23) -> 0 | O23: =General_Tanker/M_i_Y -> 166666.67 | P23: =General_Tanker/M_i_Y -> 166666.67 | Q23: =General_Tanker/M_i_Y -> 166666.67 | R23: =General_Tanker/M_i_Y -> 166666.67 | S23: =General_Tanker/M_i_Y -> 166666.67 | T23: =General_Tanker/M_i_Y -> 166666.67 | U23: =General_Tanker/M_i_Y -> 166666.67 | V23: =General_Tanker/M_i_Y -> 166666.67 | ... Z23: =General_Tanker/M_i_Y -> 166666.67 | AA23: =SUM(O23:Z23) -> 2000000 | AB23: =AA23*(Increment+Inflation_Annual) -> 2030000 | AC23: =AB23*(Increment+Inflation_Annual) -> 2060450 | AD23: =AC23*(Increment+Inflation_Annual) -> 2091356.7
A24: Stores, spares, lubricants | B24: {=Nil} -> 0 | C24: {=Nil} -> 0 | D24: {=Nil} -> 0 | E24: {=Nil} -> 0 | F24: {=Nil} -> 0 | G24: {=Nil} -> 0 | H24: {=Nil} -> 0 | I24: {=Nil} -> 0 | ... M24: {=Nil} -> 0 | N24: =SUM(B24:M24) -> 0 | O24: =Stores_Spares_Lube/M_i_Y -> 166666.67 | P24: =Stores_Spares_Lube/M_i_Y -> 166666.67 | Q24: =Stores_Spares_Lube/M_i_Y -> 166666.67 | R24: =Stores_Spares_Lube/M_i_Y -> 166666.67 | S24: =Stores_Spares_Lube/M_i_Y -> 166666.67 | T24: =Stores_Spares_Lube/M_i_Y -> 166666.67 | U24: =Stores_Spares_Lube/M_i_Y -> 166666.67 | V24: =Stores_Spares_Lube/M_i_Y -> 166666.67 | ... Z24: =Stores_Spares_Lube/M_i_Y -> 166666.67 | AA24: =SUM(O24:Z24) -> 2000000 | AB24: =AA24*(Increment+Inflation_Annual) -> 2030000 | AC24: =AB24*(Increment+Inflation_Annual) -> 2060450 | AD24: =AC24*(Increment+Inflation_Annual) -> 2091356.7
A25: Carbon Offsets | B25: {=Nil} -> 0 | C25: {=Nil} -> 0 | D25: {=Nil} -> 0 | E25: {=Nil} -> 0 | F25: {=Nil} -> 0 | G25: {=Nil} -> 0 | H25: {=Nil} -> 0 | I25: {=Nil} -> 0 | ... M25: {=Nil} -> 0 | N25: =SUM(B25:M25) -> 0 | O25: =Carbon_Offset_Tanker/M_i_Y -> 2750000 | P25: =Carbon_Offset_Tanker/M_i_Y -> 2750000 | Q25: =Carbon_Offset_Tanker/M_i_Y -> 2750000 | R25: =Carbon_Offset_Tanker/M_i_Y -> 2750000 | S25: =Carbon_Offset_Tanker/M_i_Y -> 2750000 | T25: =Carbon_Offset_Tanker/M_i_Y -> 2750000 | U25: =Carbon_Offset_Tanker/M_i_Y -> 2750000 | V25: =Carbon_Offset_Tanker/M_i_Y -> 2750000 | ... Z25: =Carbon_Offset_Tanker/M_i_Y -> 2750000 | AA25: =SUM(O25:Z25) -> 33000000 | AB25: =AA25*(Increment+Inflation_Carbon_Offset) -> 34287000 | AC25: =AB25*(Increment+Inflation_Carbon_Offset) -> 35624193 | AD25: {=AC25*(Increment+Inflation_Carbon_Offset)*Y5_Carbon_Increase} -> 74027073
A26: Special Event Costs: | AA26: =SUM(O26:Z26) -> 0
A27: Port Damage (Insurance Payout 10%) | B27: {=Nil} -> 0 | C27: {=Nil} -> 0 | D27: {=Nil} -> 0 | E27: {=Nil} -> 0 | F27: {=Nil} -> 0 | G27: {=Nil} -> 0 | H27: {=Nil} -> 0 | I27: {=Nil} -> 0 | ... M27: {=Nil} -> 0 | N27: =SUM(B27:M27) -> 0 | O27: {=Nil} -> 0 | P27: {=Nil} -> 0 | Q27: {=Nil} -> 0 | R27: {=Nil} -> 0 | S27: {=Nil} -> 0 | T27: {=Nil} -> 0 | U27: {=Nil} -> 0 | V27: {=Nil} -> 0 | ... Z27: {=Nil} -> 0 | AA27: =SUM(O27:Z27) -> 0 | AB27: {=Y3_Port_Repair*(Increment-Insurance_Cov)} -> 500000 | AC27: {=Nil} -> 0 | AD27: {=Nil} -> 0
A28: Finance: | AA28: =SUM(O28:Z28) -> 0
A29: Loan Payment | B29: ='Tanker Schedule'!$D$185 -> 0 | C29: ='Tanker Schedule'!$D$185 -> 0 | D29: ='Tanker Schedule'!$D$185 -> 0 | E29: ='Tanker Schedule'!$D$185 -> 0 | F29: ='Tanker Schedule'!$D$185 -> 0 | G29: ='Tanker Schedule'!$D$185 -> 0 | H29: ='Tanker Schedule'!$D$185 -> 0 | I29: ='Tanker Schedule'!$D$185 -> 0 | ... M29: ='Tanker Schedule'!$D$185 -> 0 | N29: =SUM(B29:M29) -> 0 | O29: {=Nil} -> 0 | P29: {=Nil} -> 0 | Q29: {=Nil} -> 0 | R29: {=Nil} -> 0 | S29: {=Nil} -> 0 | T29: {=Nil} -> 0 | U29: {=Nil} -> 0 | V29: {=Nil} -> 0 | ... Y29: {=Nil} -> 0 | Z29: ='Tanker Schedule'!D186 -> 15372204 | AA29: =SUM(O29:Z29) -> 15372204 | AB29: ='Tanker Schedule'!D187 -> 15372204 | AC29: ='Tanker Schedule'!D188 -> 15372204 | AD29: ='Tanker Schedule'!D189 -> 15372204
A30: Total Cash Outflows: | B30: =SUM(B13:B29) -> 20833333 | C30: =SUM(C13:C29) -> 20833333 | D30: =SUM(D13:D29) -> 20833333 | E30: =SUM(E13:E29) -> 20833333 | F30: =SUM(F13:F29) -> 20833333 | G30: =SUM(G13:G29) -> 20833333 | H30: =SUM(H13:H29) -> 20833333 | I30: =SUM(I13:I29) -> 20833333 | ... Z30: =SUM(Z13:Z29) -> 72383497 | AA30: =SUM(AA12:AA29) -> 6.5486987e+08 | AB30: =SUM(AB12:AB29) -> 7.2429573e+08 | AC30: =SUM(AC12:AC29) -> 7.3874304e+08 | AD30: =SUM(AD12:AD29) -> 7.9077104e+08
A32: Change in Cash | B32: =B10-B30 -> 833333.33 | C32: =C10-C30 -> 833333.33 | D32: =D10-D30 -> 833333.33 | E32: =E10-E30 -> 833333.33 | F32: =F10-F30 -> 833333.33 | G32: =G10-G30 -> 833333.33 | H32: =H10-H30 -> 833333.33 | I32: =I10-I30 -> 833333.33 | ... AD32: =AD10-AD30 -> 51161933
A33: Ending Cash Balance | B33: =B7+B32 -> 833333.33 | C33: =C7+C32 -> 1666666.7 | D33: =D7+D32 -> 2500000 | E33: =E7+E32 -> 3333333.3 | F33: =F7+F32 -> 4166666.7 | G33: =G7+G32 -> 5000000 | H33: =H7+H32 -> 5833333.3 | I33: =I7+I32 -> 6666666.7 | ... M33: =M7+M32 -> 10000000 | N33: =M33 -> 10000000 | O33: =O7+O32 -> 70031911 | P33: =P7+P32 -> 72666805 | Q33: =Q7+Q32 -> 85966655 | R33: =R7+R32 -> 92402152 | S33: =S7+S32 -> 1.0271581e+08 | T33: =T7+T32 -> 1.0915131e+08 | U33: =U7+U32 -> 1.1946497e+08 | V33: =V7+V32 -> 1.2807224e+08 | ... Z33: =Z7+Z32 -> 1.4619836e+08 | AA33: =Z33 -> 1.4619836e+08 | AB33: =AB7+AB32 -> 2.3102332e+08 | AC33: =AC7+AC32 -> 3.1764408e+08 | AD33: =AD7+AD32 -> 3.6880601e+08

Sheet Statement of Income
A1: QATAR ENERGY
A2: STATEMENT OF INCOME
A3: FOR THE FINANCIAL YEARS ENDED DECEMBER 31
B5: Year 1 | O5: Year 2 | AB5: Year 3 | AC5: Year 4 | AD5: Year 5
B6: January | C6: February | D6: March | E6: April | F6: May | G6: June | H6: July | I6: August | J6: September | K6: October | L6: November | M6: December | N6: Y1 Total | O6: January | P6: February | Q6: March | R6: April | S6: May | T6: June | U6: July | V6: August | W6: September | X6: October | Y6: November | Z6: December | AA6: Y2 Total
A7: INCOME
A8: Revenues | B8: {=Nil} -> 0 | C8: {=Nil} -> 0 | D8: {=Nil} -> 0 | E8: {=Nil} -> 0 | F8: {=Nil} -> 0 | G8: {=Nil} -> 0 | H8: {=Nil} -> 0 | I8: {=Nil} -> 0 | ... M8: {=Nil} -> 0 | N8: =SUM(B8:M8) -> 0 | O8: {=('Tanker Schedule'!D82/D_i_Y)*Days_Jan} -> 67324956 | P8: {=('Tanker Schedule'!D82/D_i_Y)*Days_Feb} -> 61352580 | Q8: {=('Tanker Schedule'!D82/D_i_Y)*Days_Mar} -> 67324956 | R8: {=('Tanker Schedule'!D82/D_i_Y)*Days_Apr} -> 65153183 | S8: {=('Tanker Schedule'!D82/D_i_Y)*Days_May} -> 67324956 | T8: {=('Tanker Schedule'!D82/D_i_Y)*Days_Jun} -> 65153183 | U8: {=('Tanker Schedule'!D82/D_i_Y)*Days_Jul} -> 67324956 | V8: {=('Tanker Schedule'!D82/D_i_Y)*Days_Aug} -> 67324956 | W8: {=('Tanker Schedule'!D82/D_i_Y)*Days_Sept} -> 65153183 | X8: {=('Tanker Schedule'!D82/D_i_Y)*Days_Oct} -> 67324956 | Y8: {=('Tanker Schedule'!D82/D_i_Y)*Days_Nov} -> 65153183 | Z8: {=('Tanker Schedule'!D82/D_i_Y)*Days_Dec} -> 67324956 | AA8: =SUM(O8:Z8) -> 7.9324e+08 | AB8: ='Tanker Schedule'!D83 -> 8.0916429e+08 | AC8: ='Tanker Schedule'!D84 -> 8.2540827e+08 | AD8: ='Tanker Schedule'!D85 -> 8.4197834e+08
A10: EXPENSES
A11: Operating Costs:
A12: LNG purchases | B12: {=Nil} -> 0 | C12: {=Nil} -> 0 | D12: {=Nil} -> 0 | E12: {=Nil} -> 0 | F12: {=Nil} -> 0 | G12: {=Nil} -> 0 | H12: {=Nil} -> 0 | I12: {=Nil} -> 0 | ... M12: {=Nil} -> 0 | N12: =SUM(B12:M12) -> 0 | O12: {='Tanker Schedule'!I82/D_i_Y*Days_Jan} -> 52898179 | P12: {='Tanker Schedule'!I82/D_i_Y*Days_Feb} -> 48205599 | Q12: {='Tanker Schedule'!I82/D_i_Y*Days_Mar} -> 52898179 | R12: {='Tanker Schedule'!I82/D_i_Y*Days_Apr} -> 51191786 | S12: {='Tanker Schedule'!I82/D_i_Y*Days_May} -> 52898179 | T12: {='Tanker Schedule'!I82/D_i_Y*Days_Jun} -> 51191786 | U12: {='Tanker Schedule'!I82/D_i_Y*Days_Jul} -> 52898179 | V12: {='Tanker Schedule'!I82/D_i_Y*Days_Aug} -> 52898179 | W12: {='Tanker Schedule'!I82/D_i_Y*Days_Sept} -> 51191786 | X12: {='Tanker Schedule'!I82/D_i_Y*Days_Oct} -> 52898179 | Y12: {='Tanker Schedule'!I82/D_i_Y*Days_Nov} -> 51191786 | Z12: {='Tanker Schedule'!I82/D_i_Y*Days_Dec} -> 52898179 | AA12: =SUM(O12:Z12) -> 6.2326e+08 | AB12: ='Tanker Schedule'!I83 -> 6.3577194e+08 | AC12: ='Tanker Schedule'!I84 -> 6.4853507e+08 | AD12: ='Tanker Schedule'!I85 -> 6.6155441e+08
A13: Port fees | B13: {=Nil} -> 0 | C13: {=Nil} -> 0 | D13: {=Nil} -> 0 | E13: {=Nil} -> 0 | F13: {=Nil} -> 0 | G13: {=Nil} -> 0 | H13: {=Nil} -> 0 | I13: {=Nil} -> 0 | ... M13: {=Nil} -> 0 | N13: =SUM(B13:M13) -> 0 | O13: ='Tanker Schedule'!$D$116/M_i_Y -> 1998333.3 | P13: ='Tanker Schedule'!$D$116/M_i_Y -> 1998333.3 | Q13: ='Tanker Schedule'!$D$116/M_i_Y -> 1998333.3 | R13: ='Tanker Schedule'!$D$116/M_i_Y -> 1998333.3 | S13: ='Tanker Schedule'!$D$116/M_i_Y -> 1998333.3 | T13: ='Tanker Schedule'!$D$116/M_i_Y -> 1998333.3 | U13: ='Tanker Schedule'!$D$116/M_i_Y -> 1998333.3 | V13: ='Tanker Schedule'!$D$116/M_i_Y -> 1998333.3 | ... Z13: ='Tanker Schedule'!$D$116/M_i_Y -> 1998333.3 | AA13: =SUM(O13:Z13) -> 23980000 | AB13: ='Tanker Schedule'!D117 -> 24563000 | AC13: ='Tanker Schedule'!D118 -> 25158094 | AD13: ='Tanker Schedule'!D119 -> 25535466
A14: Heavy fuel oil | B14: {=Nil} -> 0 | C14: {=Nil} -> 0 | D14: {=Nil} -> 0 | E14: {=Nil} -> 0 | F14: {=Nil} -> 0 | G14: {=Nil} -> 0 | H14: {=Nil} -> 0 | I14: {=Nil} -> 0 | ... M14: {=Nil} -> 0 | N14: =SUM(B14:M14) -> 0 | O14: ='Tanker Schedule'!$I$116/M_i_Y -> 82840 | P14: ='Tanker Schedule'!$I$116/M_i_Y -> 82840 | Q14: ='Tanker Schedule'!$I$116/M_i_Y -> 82840 | R14: ='Tanker Schedule'!$I$116/M_i_Y -> 82840 | S14: ='Tanker Schedule'!$I$116/M_i_Y -> 82840 | T14: ='Tanker Schedule'!$I$116/M_i_Y -> 82840 | U14: ='Tanker Schedule'!$I$116/M_i_Y -> 82840 | V14: ='Tanker Schedule'!$I$116/M_i_Y -> 82840 | ... Z14: ='Tanker Schedule'!$I$116/M_i_Y -> 82840 | AA14: =SUM(O14:Z14) -> 994080 | AB14: ='Tanker Schedule'!I117 -> 1018248 | AC14: ='Tanker Schedule'!I118 -> 1042917.4 | AD14: ='Tanker Schedule'!I119 -> 1058561.1
A15: Shipping operating costs | B15: {=Nil} -> 0 | C15: {=Nil} -> 0 | D15: {=Nil} -> 0 | E15: {=Nil} -> 0 | F15: {=Nil} -> 0 | G15: {=Nil} -> 0 | H15: {=Nil} -> 0 | I15: {=Nil} -> 0 | ... M15: {=Nil} -> 0 | N15: =SUM(B15:M15) -> 0 | O15: ='Tanker Schedule'!$D$150/M_i_Y -> 363333.33 | P15: ='Tanker Schedule'!$D$150/M_i_Y -> 363333.33 | Q15: ='Tanker Schedule'!$D$150/M_i_Y -> 363333.33 | R15: ='Tanker Schedule'!$D$150/M_i_Y -> 363333.33 | S15: ='Tanker Schedule'!$D$150/M_i_Y -> 363333.33 | T15: ='Tanker Schedule'!$D$150/M_i_Y -> 363333.33 | U15: ='Tanker Schedule'!$D$150/M_i_Y -> 363333.33 | V15: ='Tanker Schedule'!$D$150/M_i_Y -> 363333.33 | ... Z15: ='Tanker Schedule'!$D$150/M_i_Y -> 363333.33 | AA15: =SUM(O15:Z15) -> 4360000 | AB15: ='Tanker Schedule'!D151 -> 4466000 | AC15: ='Tanker Schedule'!D152 -> 4574199 | AD15: ='Tanker Schedule'!D153 -> 4642812
A16: Insurance | B16: {=Nil} -> 0 | C16: {=Nil} -> 0 | D16: {=Nil} -> 0 | E16: {=Nil} -> 0 | F16: {=Nil} -> 0 | G16: {=Nil} -> 0 | H16: {=Nil} -> 0 | I16: {=Nil} -> 0 | ... M16: {=Nil} -> 0 | N16: =SUM(B16:M16) -> 0 | O16: =Insurance_Tanker/M_i_Y -> 150000 | P16: =Insurance_Tanker/M_i_Y -> 150000 | Q16: =Insurance_Tanker/M_i_Y -> 150000 | R16: =Insurance_Tanker/M_i_Y -> 150000 | S16: =Insurance_Tanker/M_i_Y -> 150000 | T16: =Insurance_Tanker/M_i_Y -> 150000 | U16: =Insurance_Tanker/M_i_Y -> 150000 | V16: =Insurance_Tanker/M_i_Y -> 150000 | ... Z16: =Insurance_Tanker/M_i_Y -> 150000 | AA16: =SUM(O16:Z16) -> 1800000 | AB16: =AA16*(Increment+Inflation_Annual) -> 1827000 | AC16: =AB16*(Increment+Inflation_Annual) -> 1854405 | AD16: =AC16*(Increment+Inflation_Annual) -> 1882221.1
A17: Payroll - Payments to Employees | B17: {=Nil} -> 0 | C17: {=Nil} -> 0 | D17: {=Nil} -> 0 | E17: {=Nil} -> 0 | F17: {=Nil} -> 0 | G17: {=Nil} -> 0 | H17: {=Nil} -> 0 | I17: {=Nil} -> 0 | ... M17: {=Nil} -> 0 | N17: =SUM(B17:M17) -> 0 | O17: ='Tanker Schedule'!$H$48 -> 237938.6 | P17: ='Tanker Schedule'!$H$48 -> 237938.6 | Q17: ='Tanker Schedule'!$H$48 -> 237938.6 | R17: ='Tanker Schedule'!$H$48 -> 237938.6 | S17: ='Tanker Schedule'!$H$48 -> 237938.6 | T17: ='Tanker Schedule'!$H$48 -> 237938.6 | U17: ='Tanker Schedule'!$H$48 -> 237938.6 | V17: ='Tanker Schedule'!$H$48 -> 237938.6 | ... Z17: ='Tanker Schedule'!$H$48 -> 237938.6 | AA17: =SUM(O17:Z17) -> 2855263.2 | AB17: ='Tanker Schedule'!F49 -> 2898092.1 | AC17: ='Tanker Schedule'!F50 -> 2941563.5 | AD17: ='Tanker Schedule'!F51 -> 2985686.9
A18: Payroll - Remittance to Government | B18: {=Nil} -> 0 | C18: {=Nil} -> 0 | D18: {=Nil} -> 0 | E18: {=Nil} -> 0 | F18: {=Nil} -> 0 | G18: {=Nil} -> 0 | H18: {=Nil} -> 0 | I18: {=Nil} -> 0 | ... M18: {=Nil} -> 0 | N18: =SUM(B18:M18) -> 0 | O18: ='Tanker Schedule'!$I$48 -> 53728.07 | P18: ='Tanker Schedule'!$I$48 -> 53728.07 | Q18: ='Tanker Schedule'!$I$48 -> 53728.07 | R18: ='Tanker Schedule'!$I$48 -> 53728.07 | S18: ='Tanker Schedule'!$I$48 -> 53728.07 | T18: ='Tanker Schedule'!$I$48 -> 53728.07 | U18: ='Tanker Schedule'!$I$48 -> 53728.07 | V18: ='Tanker Schedule'!$I$48 -> 53728.07 | ... Z18: ='Tanker Schedule'!$I$48 -> 53728.07 | AA18: =SUM(O18:Z18) -> 644736.84 | AB18: ='Tanker Schedule'!G49 -> 654407.89 | AC18: ='Tanker Schedule'!G50 -> 664224.01 | AD18: ='Tanker Schedule'!G51 -> 674187.37
A19: Maintenance and Engineering | B19: {=Nil} -> 0 | C19: {=Nil} -> 0 | D19: {=Nil} -> 0 | E19: {=Nil} -> 0 | F19: {=Nil} -> 0 | G19: {=Nil} -> 0 | H19: {=Nil} -> 0 | I19: {=Nil} -> 0 | ... M19: {=Nil} -> 0 | N19: =SUM(B19:M19) -> 0 | O19: =General_Tanker/M_i_Y -> 166666.67 | P19: =General_Tanker/M_i_Y -> 166666.67 | Q19: =General_Tanker/M_i_Y -> 166666.67 | R19: =General_Tanker/M_i_Y -> 166666.67 | S19: =General_Tanker/M_i_Y -> 166666.67 | T19: =General_Tanker/M_i_Y -> 166666.67 | U19: =General_Tanker/M_i_Y -> 166666.67 | V19: =General_Tanker/M_i_Y -> 166666.67 | ... Z19: =General_Tanker/M_i_Y -> 166666.67 | AA19: =SUM(O19:Z19) -> 2000000 | AB19: =AA19*(Increment+Inflation_Annual) -> 2030000 | AC19: =AB19*(Increment+Inflation_Annual) -> 2060450 | AD19: =AC19*(Increment+Inflation_Annual) -> 2091356.7
A20: Stores, spares, lubricants | B20: {=Nil} -> 0 | C20: {=Nil} -> 0 | D20: {=Nil} -> 0 | E20: {=Nil} -> 0 | F20: {=Nil} -> 0 | G20: {=Nil} -> 0 | H20: {=Nil} -> 0 | I20: {=Nil} -> 0 | ... M20: {=Nil} -> 0 | N20: =SUM(B20:M20) -> 0 | O20: =Stores_Spares_Lube/M_i_Y -> 166666.67 | P20: =Stores_Spares_Lube/M_i_Y -> 166666.67 | Q20: =Stores_Spares_Lube/M_i_Y -> 166666.67 | R20: =Stores_Spares_Lube/M_i_Y -> 166666.67 | S20: =Stores_Spares_Lube/M_i_Y -> 166666.67 | T20: =Stores_Spares_Lube/M_i_Y -> 166666.67 | U20: =Stores_Spares_Lube/M_i_Y -> 166666.67 | V20: =Stores_Spares_Lube/M_i_Y -> 166666.67 | ... Z20: =Stores_Spares_Lube/M_i_Y -> 166666.67 | AA20: =SUM(O20:Z20) -> 2000000 | AB20: =AA20*(Increment+Inflation_Annual) -> 2030000 | AC20: =AB20*(Increment+Inflation_Annual) -> 2060450 | AD20: =AC20*(Increment+Inflation_Annual) -> 2091356.7
A21: Carbon offsets | B21: {=Nil} -> 0 | C21: {=Nil} -> 0 | D21: {=Nil} -> 0 | E21: {=Nil} -> 0 | F21: {=Nil} -> 0 | G21: {=Nil} -> 0 | H21: {=Nil} -> 0 | I21: {=Nil} -> 0 | ... M21: {=Nil} -> 0 | N21: =SUM(B21:M21) -> 0 | O21: =Carbon_Offset_Tanker/M_i_Y -> 2750000 | P21: =Carbon_Offset_Tanker/M_i_Y -> 2750000 | Q21: =Carbon_Offset_Tanker/M_i_Y -> 2750000 | R21: =Carbon_Offset_Tanker/M_i_Y -> 2750000 | S21: =Carbon_Offset_Tanker/M_i_Y -> 2750000 | T21: =Carbon_Offset_Tanker/M_i_Y -> 2750000 | U21: =Carbon_Offset_Tanker/M_i_Y -> 2750000 | V21: =Carbon_Offset_Tanker/M_i_Y -> 2750000 | ... Z21: =Carbon_Offset_Tanker/M_i_Y -> 2750000 | AA21: =SUM(O21:Z21) -> 33000000 | AB21: =AA21*(Increment+Inflation_Carbon_Offset) -> 34287000 | AC21: =AB21*(Increment+Inflation_Carbon_Offset) -> 35624193 | AD21: {=AC21*(Increment+Inflation_Carbon_Offset)*Y5_Carbon_Increase} -> 74027073
A22: Special Events Costs:
A23: Port damage | B23: {=Nil} -> 0 | C23: {=Nil} -> 0 | D23: {=Nil} -> 0 | E23: {=Nil} -> 0 | F23: {=Nil} -> 0 | G23: {=Nil} -> 0 | H23: {=Nil} -> 0 | I23: {=Nil} -> 0 | ... M23: {=Nil} -> 0 | N23: =SUM(B23:M23) -> 0 | O23: {=Nil} -> 0 | P23: {=Nil} -> 0 | Q23: {=Nil} -> 0 | R23: {=Nil} -> 0 | S23: {=Nil} -> 0 | T23: {=Nil} -> 0 | U23: {=Nil} -> 0 | V23: {=Nil} -> 0 | ... Z23: {=Nil} -> 0 | AA23: =SUM(O23:Z23) -> 0 | AB23: {=Y3_Port_Repair} -> 5000000 | AC23: {=Nil} -> 0 | AD23: {=Nil} -> 0
A24: Insruance payout | B24: {=Nil} -> 0 | C24: {=Nil} -> 0 | D24: {=Nil} -> 0 | E24: {=Nil} -> 0 | F24: {=Nil} -> 0 | G24: {=Nil} -> 0 | H24: {=Nil} -> 0 | I24: {=Nil} -> 0 | ... M24: {=Nil} -> 0 | N24: =SUM(B24:M24) -> 0 | O24: {=Nil} -> 0 | P24: {=Nil} -> 0 | Q24: {=Nil} -> 0 | R24: {=Nil} -> 0 | S24: {=Nil} -> 0 | T24: {=Nil} -> 0 | U24: {=Nil} -> 0 | V24: {=Nil} -> 0 | ... Z24: {=Nil} -> 0 | AA24: =SUM(O24:Z24) -> 0 | AB24: {=-Y3_Port_Repair*Insurance_Cov} -> -4500000 | AC24: {=Nil} -> 0 | AD24: {=Nil} -> 0
A25: TOTAL EXPENSES | B25: =SUM(B12:B24) -> 0 | C25: =SUM(C12:C24) -> 0 | D25: =SUM(D12:D24) -> 0 | E25: =SUM(E12:E24) -> 0 | F25: =SUM(F12:F24) -> 0 | G25: =SUM(G12:G24) -> 0 | H25: =SUM(H12:H24) -> 0 | I25: =SUM(I12:I24) -> 0 | ... AD25: =SUM(AD12:AD24) -> 7.7654313e+08
A27: EBITDA | B27: =B8-B25 -> 0 | C27: =C8-C25 -> 0 | D27: =D8-D25 -> 0 | E27: =E8-E25 -> 0 | F27: =F8-F25 -> 0 | G27: =G8-G25 -> 0 | H27: =H8-H25 -> 0 | I27: =I8-I25 -> 0 | ... AD27: =AD8-AD25 -> 65435208
A29: Interest | B29: {=TRANSPOSE('Tanker Schedule'!J185:J196)} -> 102777.78 | C29: 172222.22 | D29: 241666.67 | E29: 311111.11 | F29: 380555.56 | G29: 450000 | H29: 519444.44 | I29: 588888.89 | J29: 658333.33 | K29: 727777.78 | L29: 797222.22 | M29: 866666.67 | N29: =SUM(B29:M29) -> 5816666.7 | O29: ='Tanker Schedule'!$C$186/M_i_Y -> 886055.56 | P29: ='Tanker Schedule'!$C$186/M_i_Y -> 886055.56 | Q29: ='Tanker Schedule'!$C$186/M_i_Y -> 886055.56 | R29: ='Tanker Schedule'!$C$186/M_i_Y -> 886055.56 | S29: ='Tanker Schedule'!$C$186/M_i_Y -> 886055.56 | T29: ='Tanker Schedule'!$C$186/M_i_Y -> 886055.56 | U29: ='Tanker Schedule'!$C$186/M_i_Y -> 886055.56 | V29: ='Tanker Schedule'!$C$186/M_i_Y -> 886055.56 | ... Z29: ='Tanker Schedule'!$C$186/M_i_Y -> 886055.56 | AA29: =SUM(O29:Z29) -> 10632667 | AB29: ='Tanker Schedule'!C187 -> 10443085 | AC29: ='Tanker Schedule'!C188 -> 10245920 | AD29: ='Tanker Schedule'!C189 -> 10040869
A30: Depreciation | B30: {=Nil} -> 0 | C30: {=Nil} -> 0 | D30: {=Nil} -> 0 | E30: {=Nil} -> 0 | F30: {=Nil} -> 0 | G30: {=Nil} -> 0 | H30: {=Nil} -> 0 | I30: {=Nil} -> 0 | ... M30: {=Nil} -> 0 | N30: =SUM(B30:M30) -> 0 | O30: ='Tanker Schedule'!$C$14/M_i_Y -> 638888.89 | P30: ='Tanker Schedule'!$C$14/M_i_Y -> 638888.89 | Q30: ='Tanker Schedule'!$C$14/M_i_Y -> 638888.89 | R30: ='Tanker Schedule'!$C$14/M_i_Y -> 638888.89 | S30: ='Tanker Schedule'!$C$14/M_i_Y -> 638888.89 | T30: ='Tanker Schedule'!$C$14/M_i_Y -> 638888.89 | U30: ='Tanker Schedule'!$C$14/M_i_Y -> 638888.89 | V30: ='Tanker Schedule'!$C$14/M_i_Y -> 638888.89 | ... Z30: ='Tanker Schedule'!$C$14/M_i_Y -> 638888.89 | AA30: =SUM(O30:Z30) -> 7666666.7 | AB30: ='Tanker Schedule'!C15 -> 7666666.7 | AC30: ='Tanker Schedule'!C16 -> 7666666.7 | AD30: ='Tanker Schedule'!C17 -> 7666666.7
A32: NET INCOME | B32: =B27-B29-B30 -> -102777.78 | C32: =C27-C29-C30 -> -172222.22 | D32: =D27-D29-D30 -> -241666.67 | E32: =E27-E29-E30 -> -311111.11 | F32: =F27-F29-F30 -> -380555.56 | G32: =G27-G29-G30 -> -450000 | H32: =H27-H29-H30 -> -519444.44 | I32: =I27-I29-I30 -> -588888.89 | ... AD32: =AD27-AD29-AD30 -> 47727673

Sheet Statement of Financial Position
A1: QATAR ENERGY
A2: STATEMENT OF FINANCIAL POSITION
A3: FOR THE FINANCIAL YEARS ENDED DECEMBER 31
B5: Year 1 | C5: Year 2 | D5: Year 3 | E5: Year 4 | F5: Year 5
A6: ASSETS
A8: Cash | B8: ='Cash Budget'!N33 -> 10000000 | C8: ='Cash Budget'!AA33 -> 1.4619836e+08 | D8: ='Cash Budget'!AB33 -> 2.3102332e+08 | E8: ='Cash Budget'!AC33 -> 3.1764408e+08 | F8: ='Cash Budget'!AD33 -> 3.6880601e+08
A9: Accounts Receivable | C9: ='Tanker Schedule'!D82/D_i_Y -> 2171772.8 | D9: ='Tanker Schedule'!D83/D_i_Y -> 2215371.1 | E9: ='Tanker Schedule'!D84/D_i_Y -> 2259844.7 | F9: ='Tanker Schedule'!D85/D_i_Y -> 2305211.1
A10: Fixed Assets | B10: =Building_Cost_Tanker -> 250000000 | C10: =Building_Cost_Tanker -> 250000000 | D10: =Building_Cost_Tanker -> 250000000 | E10: =Building_Cost_Tanker -> 250000000 | F10: =Building_Cost_Tanker -> 250000000
A11: less Accumulated Depreciation | C11: =-(Annual_Depreciation_Tanker) -> -7666666.7 | D11: =-(Annual_Depreciation_Tanker-C11) -> -15333333 | E11: =-(Annual_Depreciation_Tanker-D11) -> -23000000 | F11: =-(Annual_Depreciation_Tanker-E11) -> -30666667
A13: TOTAL ASSETS | B13: =SUM(B8:B11) -> 2.6e+08 | C13: =SUM(C8:C11) -> 3.9070346e+08 | D13: =SUM(D8:D11) -> 4.6790536e+08 | E13: =SUM(E8:E11) -> 5.4690392e+08 | F13: =SUM(F8:F11) -> 5.9044456e+08
A15: LIABILITES
A17: Employer Remittance Payable | C17: ='Tanker Schedule'!I48 -> 53728.07 | D17: ='Tanker Schedule'!I49 -> 54533.991 | E17: ='Tanker Schedule'!I50 -> 55352.001 | F17: ='Tanker Schedule'!I51 -> 56182.281
A18: LNG Payable | C18: {=('Tanker Schedule'!I82/D_i_Y)*Days_Dec} -> 52898179 | D18: {=('Tanker Schedule'!I83/D_i_Y)*Days_Dec} -> 53960110 | E18: {=('Tanker Schedule'!I84/D_i_Y)*Days_Dec} -> 55043359 | F18: {=('Tanker Schedule'!I85/D_i_Y)*Days_Dec} -> 56148355
A19: Port Fees Payable | C19: ='Tanker Schedule'!D116/M_i_Y -> 1998333.3 | D19: ='Tanker Schedule'!D117/M_i_Y -> 2046916.7 | E19: ='Tanker Schedule'!D118/M_i_Y -> 2096507.9 | F19: ='Tanker Schedule'!D119/M_i_Y -> 2127955.5
A20: Heavy Fuel Oil Payable | C20: ='Tanker Schedule'!I116/M_i_Y -> 82840 | D20: ='Tanker Schedule'!I117/M_i_Y -> 84854 | E20: ='Tanker Schedule'!I118/M_i_Y -> 86909.781 | F20: ='Tanker Schedule'!I119/M_i_Y -> 88213.428
A21: Shipping Operating Expense Payable | C21: ='Tanker Schedule'!D150/M_i_Y -> 363333.33 | D21: ='Tanker Schedule'!D151/M_i_Y -> 372166.67 | E21: ='Tanker Schedule'!D152/M_i_Y -> 381183.25 | F21: ='Tanker Schedule'!D153/M_i_Y -> 386901
A22: Bank Loan O/S | B22: ='Tanker Schedule'!F185 -> 2.6581667e+08 | C22: ='Tanker Schedule'!F186 -> 2.6107713e+08 | D22: ='Tanker Schedule'!F187 -> 2.5614801e+08 | E22: ='Tanker Schedule'!F188 -> 2.5102173e+08 | F22: ='Tanker Schedule'!F189 -> 2.4569039e+08
A24: SHAREHOLDERS EQUITY
A26: Retained Earnings | B26: ='Statement of Income'!N32 -> -5816666.7 | C26: ='Statement of Income'!AA32+B26 -> 74229920 | D26: ='Statement of Income'!AB32+C26 -> 1.5523877e+08 | E26: ='Statement of Income'!AC32+D26 -> 2.3821889e+08 | F26: ='Statement of Income'!AD32+E26 -> 2.8594656e+08
A28: TOTAL LIABILITES AND SHAREHOLDERS EQUITY | B28: =SUM(B17:B26) -> 260000000 | C28: =SUM(C17:C26) -> 3.9070346e+08 | D28: =SUM(D17:D26) -> 4.6790536e+08 | E28: =SUM(E17:E26) -> 5.4690392e+08 | F28: =SUM(F17:F26) -> 5.9044456e+08
A30: Check Sum | B30: =B13-B28 -> 0 | C30: =C13-C28 -> 0 | D30: =D13-D28 -> 0 | E30: =E13-E28 -> 0 | F30: =F13-F28 -> 0

Sheet NPV (Y2-Y31)
A1: QATAR ENERGY
A2: 30-YR NPV COMPARISON (PIPELINE Vs. TANKER)
A4: CASH FLOW - PIPELINE
B5: Y2 | C5: Y3 | D5: Y4 | E5: Y5 | F5: Y6 | G5: Y7 | H5: Y8 | I5: Y9 | J5: Y10 | K5: Y11 | L5: Y12 | M5: Y13 | N5: Y14 | O5: Y15 | P5: Y16 | Q5: Y17 | R5: Y18 | S5: Y19 | T5: Y20 | U5: Y21 | V5: Y22 | W5: Y23 | X5: Y24 | Y5: Y25 | Z5: Y26 | AA5: Y27 | AB5: Y28 | AC5: Y29 | AD5: Y30 | AE5: Y31
A6: Revenue:
A7: Sales | B7: {=TRANSPOSE('Pipeline Schedule'!D49:D78)} -> 884000000 | C7: 9.017463e+08 | D7: 9.1984886e+08 | E7: 9.3831482e+08 | F7: 9.5715149e+08 | G7: 9.7636631e+08 | H7: 9.9596686e+08 | I7: 1.0159609e+09 | J7: 1.0363563e+09 | K7: 1.0571612e+09 | L7: 1.0783837e+09 | M7: 1.1000322e+09 | N7: 1.1221154e+09 | O7: 1.1446418e+09 | P7: 1.1676205e+09 | Q7: 1.1910605e+09 | R7: 1.214971e+09 | S7: 1.2393616e+09 | T7: 1.2642418e+09 | U7: 1.2896214e+09 | V7: 1.3155106e+09 | W7: 1.3419195e+09 | X7: 1.3688585e+09 | Y7: 1.3963383e+09 | Z7: 1.4243698e+09 | AA7: 1.452964e+09 | AB7: 1.4821323e+09 | AC7: 1.5118861e+09 | AD7: 1.5422372e+09 | AE7: 1.5731976e+09
A8: Less: COGS | B8: {=TRANSPOSE('Pipeline Schedule'!I49:I78)} -> 782000000 | C8: 7.9769865e+08 | D8: 8.1371245e+08 | E8: 8.3004773e+08 | F8: 8.4671094e+08 | G8: 8.6370866e+08 | H8: 8.8104761e+08 | I8: 8.9873464e+08 | J8: 9.1677674e+08 | K8: 9.3518103e+08 | L8: 9.5395479e+08 | M8: 9.7310543e+08 | N8: 9.9264052e+08 | O8: 1.0125678e+09 | P8: 1.0328951e+09 | Q8: 1.0536304e+09 | R8: 1.0747821e+09 | S8: 1.0963583e+09 | T8: 1.1183677e+09 | U8: 1.140819e+09 | V8: 1.1637209e+09 | W8: 1.1870826e+09 | X8: 1.2109133e+09 | Y8: 1.2352224e+09 | Z8: 1.2600195e+09 | AA8: 1.2853143e+09 | AB8: 1.311117e+09 | AC8: 1.3374377e+09 | AD8: 1.3642868e+09 | AE8: 1.3916748e+09
A9: Salvage Value | B9: {=Nil} -> 0 | C9: {=Nil} -> 0 | D9: {=Nil} -> 0 | E9: {=Nil} -> 0 | F9: {=Nil} -> 0 | G9: {=Nil} -> 0 | H9: {=Nil} -> 0 | I9: {=Nil} -> 0 | ... AD9: {=Nil} -> 0 | AE9: =Salvage_Val_Pipeline -> 15000000
A10: Total | B10: =B7-B8+B9 -> 102000000 | C10: =C7-C8+C9 -> 1.0404765e+08 | D10: =D7-D8+D9 -> 1.0613641e+08 | E10: =E7-E8+E9 -> 1.0826709e+08 | F10: =F7-F8+F9 -> 1.1044056e+08 | G10: =G7-G8+G9 -> 1.1265765e+08 | H10: =H7-H8+H9 -> 1.1491925e+08 | I10: =I7-I8+I9 -> 1.1722626e+08 | ... AE10: =AE7-AE8+AE9 -> 1.965228e+08
A12: Expenses:
A13: Insurance | B13: =Insurance_Pipeline -> 2200000 | C13: =B13*(Increment+Inflation_Annual) -> 2233000 | D13: =C13*(Increment+Inflation_Annual) -> 2266495 | E13: =D13*(Increment+Inflation_Annual) -> 2300492.4 | F13: =E13*(Increment+Inflation_Annual) -> 2334999.8 | G13: =F13*(Increment+Inflation_Annual) -> 2370024.8 | H13: =G13*(Increment+Inflation_Annual) -> 2405575.2 | I13: =H13*(Increment+Inflation_Annual) -> 2441658.8 | J13: =I13*(Increment+Inflation_Annual) -> 2478283.7 | ... AE13: =AD13*(Increment+Inflation_Annual) -> 3387957.1
A14: Operatings Management | B14: =Operations_Mgmt -> 1000000 | C14: =B14*(Increment+Inflation_Annual) -> 1015000 | D14: =C14*(Increment+Inflation_Annual) -> 1030225 | E14: =D14*(Increment+Inflation_Annual) -> 1045678.4 | F14: =E14*(Increment+Inflation_Annual) -> 1061363.6 | G14: =F14*(Increment+Inflation_Annual) -> 1077284 | H14: =G14*(Increment+Inflation_Annual) -> 1093443.3 | I14: =H14*(Increment+Inflation_Annual) -> 1109844.9 | J14: =I14*(Increment+Inflation_Annual) -> 1126492.6 | ... AE14: =AD14*(Increment+Inflation_Annual) -> 1539980.5
A15: Fuel Compression and Pumping Expense | B15: {=TRANSPOSE('Pipeline Schedule'!C84:C113)} -> 391666.67 | C15: 397541.67 | D15: 403504.79 | E15: 409557.36 | F15: 415700.72 | G15: 421936.23 | H15: 428265.28 | I15: 434689.26 | J15: 441209.6 | K15: 447827.74 | L15: 454545.16 | M15: 461363.33 | N15: 468283.78 | O15: 475308.04 | P15: 482437.66 | Q15: 489674.23 | R15: 497019.34 | S15: 504474.63 | T15: 512041.75 | U15: 519722.38 | V15: 527518.21 | W15: 535430.98 | X15: 543462.45 | Y15: 551614.39 | Z15: 559888.6 | AA15: 568286.93 | AB15: 576811.23 | AC15: 585463.4 | AD15: 594245.35 | AE15: 603159.03
A16: Maintenance and Engineering | B16: {=General_Main_Eng} -> 12000000 | C16: =B16*(Increment+Inflation_Annual) -> 12180000 | D16: =C16*(Increment+Inflation_Annual) -> 12362700 | E16: =D16*(Increment+Inflation_Annual) -> 12548140 | F16: =E16*(Increment+Inflation_Annual) -> 12736363 | G16: =F16*(Increment+Inflation_Annual) -> 12927408 | H16: =G16*(Increment+Inflation_Annual) -> 13121319 | I16: =H16*(Increment+Inflation_Annual) -> 13318139 | J16: =I16*(Increment+Inflation_Annual) -> 13517911 | ... AE16: =AD16*(Increment+Inflation_Annual) -> 18479766
A17: Carbon Offsets | B17: =General_Pipeline -> 800000 | C17: =B17*(Increment+Inflation_Carbon_Offset) -> 831200 | D17: =C17*(Increment+Inflation_Carbon_Offset) -> 863616.8 | E17: =D17*(Increment+Inflation_Carbon_Offset) -> 897297.86 | F17: =E17*(Increment+Inflation_Carbon_Offset) -> 932292.47 | G17: =F17*(Increment+Inflation_Carbon_Offset) -> 968651.88 | H17: =G17*(Increment+Inflation_Carbon_Offset) -> 1006429.3 | I17: =H17*(Increment+Inflation_Carbon_Offset) -> 1045680 | J17: =I17*(Increment+Inflation_Carbon_Offset) -> 1086461.6 | ... AE17: =AD17*(Increment+Inflation_Carbon_Offset) -> 2426279.7
A18: Total | B18: =SUM(B13:B16) -> 15591667 | C18: =SUM(C13:C16) -> 15825542 | D18: =SUM(D13:D16) -> 16062925 | E18: =SUM(E13:E16) -> 16303869 | F18: =SUM(F13:F16) -> 16548427 | G18: =SUM(G13:G16) -> 16796653 | H18: =SUM(H13:H16) -> 17048603 | I18: =SUM(I13:I16) -> 17304332 | ... AE18: =SUM(AE13:AE16) -> 24010863
A20: Net Cash Flows | B20: =B10-B18 -> 86408333 | C20: =C10-C18 -> 88222108 | D20: =D10-D18 -> 90073482 | E20: =E10-E18 -> 91963226 | F20: =F10-F18 -> 93892130 | G20: =G10-G18 -> 95860998 | H20: =H10-H18 -> 97870651 | I20: =I10-I18 -> 99921925 | ... AE20: =AE10-AE18 -> 1.7251194e+08
A22: CASH FLOW - TANKER
B23: Y2 | C23: Y3 | D23: Y4 | E23: Y5 | F23: Y6 | G23: Y7 | H23: Y8 | I23: Y9 | J23: Y10 | K23: Y11 | L23: Y12 | M23: Y13 | N23: Y14 | O23: Y15 | P23: Y16 | Q23: Y17 | R23: Y18 | S23: Y19 | T23: Y20 | U23: Y21 | V23: Y22 | W23: Y23 | X23: Y24 | Y23: Y25 | Z23: Y26 | AA23: Y27 | AB23: Y28 | AC23: Y29 | AD23: Y30 | AE23: Y31
A24: Revenue:
A25: Sales | B25: {=TRANSPOSE('Tanker Schedule'!D82:D111)} -> 793240000 | C25: 8.0916429e+08 | D25: 8.2540827e+08 | E25: 8.4197834e+08 | F25: 8.5888105e+08 | G25: 8.7612309e+08 | H25: 8.9371126e+08 | I25: 9.1165251e+08 | J25: 9.2995394e+08 | K25: 9.4862276e+08 | L25: 9.6766637e+08 | M25: 9.8709227e+08 | N25: 1.0069081e+09 | O25: 1.0271218e+09 | P25: 1.0477413e+09 | Q25: 1.0687747e+09 | R25: 1.0902304e+09 | S25: 1.1121167e+09 | T25: 1.1344425e+09 | U25: 1.1572164e+09 | V25: 1.1804475e+09 | W25: 1.204145e+09 | X25: 1.2283182e+09 | Y25: 1.2529767e+09 | Z25: 1.2781302e+09 | AA25: 1.3037887e+09 | AB25: 1.3299622e+09 | AC25: 1.3566612e+09 | AD25: 1.3838962e+09 | AE25: 1.4116779e+09
A26: Less: COGS | B26: {=TRANSPOSE('Tanker Schedule'!I82:I111)} -> 623260000 | C26: 6.3577194e+08 | D26: 6.4853507e+08 | E26: 6.6155441e+08 | F26: 6.7483511e+08 | G26: 6.8838243e+08 | H26: 7.022017e+08 | I26: 7.162984e+08 | J26: 7.3067809e+08 | K26: 7.4534646e+08 | L26: 7.6030929e+08 | M26: 7.755725e+08 | N26: 7.9114211e+08 | O26: 8.0702429e+08 | P26: 8.232253e+08 | Q26: 8.3975155e+08 | R26: 8.5660956e+08 | S26: 8.73806e+08 | T26: 8.9134766e+08 | U26: 9.0924146e+08 | V26: 9.2749448e+08 | W26: 9.4611394e+08 | X26: 9.6510717e+08 | Y26: 9.844817e+08 | Z26: 1.0042452e+09 | AA26: 1.0244054e+09 | AB26: 1.0449703e+09 | AC26: 1.0659481e+09 | AD26: 1.087347e+09 | AE26: 1.1091755e+09
A27: Salvage Value | B27: {=Nil} -> 0 | C27: {=Nil} -> 0 | D27: {=Nil} -> 0 | E27: {=Nil} -> 0 | F27: {=Nil} -> 0 | G27: {=Nil} -> 0 | H27: {=Nil} -> 0 | I27: {=Nil} -> 0 | ... AD27: {=Nil} -> 0 | AE27: =Salvage_Val_Tanker -> 20000000
A28: Total | B28: =B25-B26+B27 -> 169980000 | C28: =C25-C26+C27 -> 1.7339235e+08 | D28: =D25-D26+D27 -> 1.768732e+08 | E28: =E25-E26+E27 -> 1.8042393e+08 | F28: =F25-F26+F27 -> 1.8404594e+08 | G28: =G25-G26+G27 -> 1.8774066e+08 | H28: =H25-H26+H27 -> 1.9150956e+08 | I28: =I25-I26+I27 -> 1.9535411e+08 | ... AE28: =AE25-AE26+AE27 -> 3.2250241e+08
A30: Direct Costs:
A31: Port fees | B31: {=TRANSPOSE('Tanker Schedule'!D116:D145)} -> 23980000 | C31: 24563000 | D31: 25158094 | E31: 25535466 | F31: 26151998 | G31: 26544278 | H31: 27183000 | I31: 27590745 | J31: 28252434 | K31: 28676221 | L31: 29361683 | M31: 30061257 | N31: 30512176 | O31: 31236840 | P31: 31705393 | Q31: 32456024 | R31: 33222042 | S31: 33720372 | T31: 34513793 | U31: 35031500 | V31: 35853280 | W31: 36391079 | X31: 37242210 | Y31: 38110686 | Z31: 38682346 | AA31: 39581789 | AB31: 40499512 | AC31: 41107005 | AD31: 42057399 | AE31: 42688260
A32: Heavy Fuel Oil | B32: {=TRANSPOSE('Tanker Schedule'!I116:I145)} -> 994080 | C32: 1018248 | D32: 1042917.4 | E32: 1058561.1 | F32: 1084119.2 | G32: 1100381 | H32: 1126858.9 | I32: 1143761.8 | J32: 1171191.8 | K32: 1188759.7 | L32: 1217175.2 | M32: 1246175.7 | N32: 1264868.4 | O32: 1294909 | P32: 1314332.6 | Q32: 1345449.7 | R32: 1377204.6 | S32: 1397862.7 | T32: 1430753.6 | U32: 1452214.9 | V32: 1486281.4 | W32: 1508575.7 | X32: 1543858.9 | Y32: 1579861.2 | Z32: 1603559.1 | AA32: 1640845.1 | AB32: 1678888.9 | AC32: 1704072.2 | AD32: 1743470.4 | AE32: 1769622.4
A33: Shipping Operating Expense | B33: {=TRANSPOSE('Tanker Schedule'!D150:D179)} -> 4360000 | C33: 4466000 | D33: 4574199 | E33: 4642812 | F33: 4754908.7 | G33: 4826232.3 | H33: 4942363.6 | I33: 5016499 | J33: 5136806.2 | K33: 5213858.3 | L33: 5338487.8 | M33: 5465683.1 | N33: 5547668.3 | O33: 5679425.4 | P33: 5764616.8 | Q33: 5901095.4 | R33: 6040371.2 | S33: 6130976.8 | T33: 6275235.1 | U33: 6369363.6 | V33: 6518778.2 | W33: 6616559.9 | X33: 6771310.9 | Y33: 6929215.6 | Z33: 7033153.8 | AA33: 7196689 | AB33: 7363547.7 | AC33: 7474000.9 | AD33: 7646799.8 | AE33: 7761501.8
B34: =SUM(B31:B33) -> 29334080 | C34: =SUM(C31:C33) -> 30047248 | D34: =SUM(D31:D33) -> 30775211 | E34: =SUM(E31:E33) -> 31236839 | F34: =SUM(F31:F33) -> 31991026 | G34: =SUM(G31:G33) -> 32470891 | H34: =SUM(H31:H33) -> 33252222 | I34: =SUM(I31:I33) -> 33751005 | ... AE34: =SUM(AE31:AE33) -> 52219384
A35: Expenses:
A36: Insurance | B36: =Insurance_Tanker -> 1800000 | C36: =B36*(Increment+Inflation_Annual) -> 1827000 | D36: =C36*(Increment+Inflation_Annual) -> 1854405 | E36: =D36*(Increment+Inflation_Annual) -> 1882221.1 | F36: =E36*(Increment+Inflation_Annual) -> 1910454.4 | G36: =F36*(Increment+Inflation_Annual) -> 1939111.2 | H36: =G36*(Increment+Inflation_Annual) -> 1968197.9 | I36: =H36*(Increment+Inflation_Annual) -> 1997720.8 | J36: =I36*(Increment+Inflation_Annual) -> 2027686.7 | ... AE36: =AD36*(Increment+Inflation_Annual) -> 2771964.9
A37: Wages/Payroll Expense | B37: {=TRANSPOSE('Tanker Schedule'!B48:B77)} -> 3500000 | C37: 3552500 | D37: 3605787.5 | E37: 3659874.3 | F37: 3714772.4 | G37: 3770494 | H37: 3827051.4 | I37: 3884457.2 | J37: 3942724.1 | K37: 4001864.9 | L37: 4061892.9 | M37: 4122821.3 | N37: 4184663.6 | O37: 4247433.6 | P37: 4311145.1 | Q37: 4375812.2 | R37: 4441449.4 | S37: 4508071.2 | T37: 4575692.2 | U37: 4644327.6 | V37: 4713992.5 | W37: 4784702.4 | X37: 4856472.9 | Y37: 4929320 | Z37: 5003259.8 | AA37: 5078308.7 | AB37: 5154483.4 | AC37: 5231800.6 | AD37: 5310277.6 | AE37: 5389931.8
A38: Maintenance and Engineering | B38: =General_Tanker -> 2000000 | C38: =B38*(Increment+Inflation_Annual) -> 2030000 | D38: =C38*(Increment+Inflation_Annual) -> 2060450 | E38: =D38*(Increment+Inflation_Annual) -> 2091356.7 | F38: =E38*(Increment+Inflation_Annual) -> 2122727.1 | G38: =F38*(Increment+Inflation_Annual) -> 2154568 | H38: =G38*(Increment+Inflation_Annual) -> 2186886.5 | I38: =H38*(Increment+Inflation_Annual) -> 2219689.8 | J38: =I38*(Increment+Inflation_Annual) -> 2252985.2 | ... AE38: =AD38*(Increment+Inflation_Annual) -> 3079961
A39: Stores, spares, lubricants | B39: =Stores_Spares_Lube -> 2000000 | C39: =B39*(Increment+Inflation_Annual) -> 2030000 | D39: =C39*(Increment+Inflation_Annual) -> 2060450 | E39: =D39*(Increment+Inflation_Annual) -> 2091356.7 | F39: =E39*(Increment+Inflation_Annual) -> 2122727.1 | G39: =F39*(Increment+Inflation_Annual) -> 2154568 | H39: =G39*(Increment+Inflation_Annual) -> 2186886.5 | I39: =H39*(Increment+Inflation_Annual) -> 2219689.8 | J39: =I39*(Increment+Inflation_Annual) -> 2252985.2 | ... AE39: =AD39*(Increment+Inflation_Annual) -> 3079961
A40: Carbon Offsets | B40: =Carbon_Offset_Tanker -> 33000000 | C40: =B40*(Increment+Inflation_Carbon_Offset) -> 34287000 | D40: =C40*(Increment+Inflation_Carbon_Offset) -> 35624193 | E40: =D40*(Increment+Inflation_Carbon_Offset) -> 37013537 | F40: =E40*(Increment+Inflation_Carbon_Offset) -> 38457064 | G40: =F40*(Increment+Inflation_Carbon_Offset) -> 39956890 | H40: =G40*(Increment+Inflation_Carbon_Offset) -> 41515209 | I40: =H40*(Increment+Inflation_Carbon_Offset) -> 43134302 | J40: =I40*(Increment+Inflation_Carbon_Offset) -> 44816540 | ... AE40: =AD40*(Increment+Inflation_Carbon_Offset) -> 1.0008404e+08
B41: =SUM(B36:B40) -> 42300000 | C41: =SUM(C36:C40) -> 43726500 | D41: =SUM(D36:D40) -> 45205286 | E41: =SUM(E36:E40) -> 46738345 | F41: =SUM(F36:F40) -> 48327745 | G41: =SUM(G36:G40) -> 49975631 | H41: =SUM(H36:H40) -> 51684231 | I41: =SUM(I36:I40) -> 53455860 | ... AE41: =SUM(AE36:AE40) -> 1.1440586e+08
A43: Net Cash Flows | B43: =B28-B34-B41 -> 98345920 | C43: =C28-C34-C41 -> 99618600 | D43: =D28-D34-D41 -> 1.008927e+08 | E43: =E28-E34-E41 -> 1.0244874e+08 | F43: =F28-F34-F41 -> 1.0372717e+08 | G43: =G28-G34-G41 -> 1.0529414e+08 | H43: =H28-H34-H41 -> 1.065731e+08 | I43: =I28-I34-I41 -> 1.0814725e+08 | ... AE43: =AE28-AE34-AE41 -> 1.5587717e+08
A45: NPV SCHEDULE (30 YEARS)
A46: Date | B46: Number of Years | C46: Pipeline Net Cash Flows | D46: Present Value | E46: Tanker Net Cash Flows | F46: Present Value
A47: Year 1 | B47: =Increment-Set_Up_Year -> 0 | C47: {=-(Pipeline_TotalCost)} -> -520000000 | D47: {=Nil} -> 0 | E47: =-(Building_Cost_Tanker) -> -250000000 | F47: {=Nil} -> 0
A48: Year 2 | B48: =Set_Up_Year -> 1 | C48: {=TRANSPOSE(B20:AE20)} -> 86408333 | D48: =C48*(Increment/(Increment+Discount_Rate)^B48) -> 83084936 | E48: {=TRANSPOSE(B43:AE43)} -> 98345920 | F48: =E48*(Increment/(Increment+Discount_Rate)^B48) -> 94563385
A49: Year 3 | B49: =Set_Up_Year+Increment -> 2 | C49: 88222108 | D49: =C49*(Increment/(Increment+Discount_Rate)^B49) -> 81566298 | E49: 99618600 | F49: =E49*(Increment/(Increment+Discount_Rate)^B49) -> 92102996
A50: Year 4 | B50: =B49+Increment -> 3 | C50: 90073482 | D50: =C50*(Increment/(Increment+Discount_Rate)^B50) -> 80074997 | E50: 1.008927e+08 | F50: =E50*(Increment/(Increment+Discount_Rate)^B50) -> 89693246
A51: Year 5 | B51: =B50+Increment -> 4 | C51: 91963226 | D51: =C51*(Increment/(Increment+Discount_Rate)^B51) -> 78610551 | E51: 1.0244874e+08 | F51: =E51*(Increment/(Increment+Discount_Rate)^B51) -> 87573617
A52: Year 6 | B52: =B51+Increment -> 5 | C52: 93892130 | D52: =C52*(Increment/(Increment+Discount_Rate)^B52) -> 77172487 | E52: 1.0372717e+08 | F52: =E52*(Increment/(Increment+Discount_Rate)^B52) -> 85256172
A53: Year 7 | B53: =B52+Increment -> 6 | C53: 95860998 | D53: =C53*(Increment/(Increment+Discount_Rate)^B53) -> 75760339 | E53: 1.0529414e+08 | F53: =E53*(Increment/(Increment+Discount_Rate)^B53) -> 83215488
A54: Year 8 | B54: =B53+Increment -> 7 | C54: 97870651 | D54: =C54*(Increment/(Increment+Discount_Rate)^B54) -> 74373651 | E54: 1.065731e+08 | F54: =E54*(Increment/(Increment+Discount_Rate)^B54) -> 80986799
A55: Year 9 | B55: =B54+Increment -> 8 | C55: 99921925 | D55: =C55*(Increment/(Increment+Discount_Rate)^B55) -> 73011972 | E55: 1.0814725e+08 | F55: =E55*(Increment/(Increment+Discount_Rate)^B55) -> 79022133
A56: Year 10 | B56: =B55+Increment -> 9 | C56: 1.0201568e+08 | D56: =C56*(Increment/(Increment+Discount_Rate)^B56) -> 71674862 | E56: 1.0942249e+08 | F56: =E56*(Increment/(Increment+Discount_Rate)^B56) -> 76878791
A57: Year 11 | B57: =B56+Increment -> 10 | C57: 1.0415278e+08 | D57: =C57*(Increment/(Increment+Discount_Rate)^B57) -> 70361886 | E57: 1.1099956e+08 | F57: =E57*(Increment/(Increment+Discount_Rate)^B57) -> 74987323
A58: Year 12 | B58: =B57+Increment -> 11 | C58: 1.0633412e+08 | D58: =C58*(Increment/(Increment+Discount_Rate)^B58) -> 69072617 | E58: 1.1226631e+08 | F58: =E58*(Increment/(Increment+Discount_Rate)^B58) -> 72926052
A59: Year 13 | B59: =B58+Increment -> 12 | C59: 1.0856061e+08 | D59: =C59*(Increment/(Increment+Discount_Rate)^B59) -> 67806636 | E59: 1.135245e+08 | F59: =E59*(Increment/(Increment+Discount_Rate)^B59) -> 70907068
A60: Year 14 | B60: =B59+Increment -> 13 | C60: 1.1083317e+08 | D60: =C60*(Increment/(Increment+Discount_Rate)^B60) -> 66563530 | E60: 1.1509442e+08 | F60: =E60*(Increment/(Increment+Discount_Rate)^B60) -> 69122724
A61: Year 15 | B61: =B60+Increment -> 14 | C61: 1.1315275e+08 | D61: =C61*(Increment/(Increment+Discount_Rate)^B61) -> 65342896 | E61: 1.1633579e+08 | F61: =E61*(Increment/(Increment+Discount_Rate)^B61) -> 67181020
... A77: Year 31 | B77: =B76+Increment -> 30 | C77: 1.7251194e+08 | D77: =C77*(Increment/(Increment+Discount_Rate)^B77) -> 53188651 | E77: 1.5587717e+08 | F77: =E77*(Increment/(Increment+Discount_Rate)^B77) -> 48059842
C78: NPV | D78: =NPV(Discount_Rate,D48:D77)-C47 -> 1.6938693e+09 | E78: NPV | F78: =SUM(F47:F77) -> 1.980071e+09
